{
  "search_metadata": {
    "id": "670a2f6ba775f2c583499ec8",
    "status": "Success",
    "json_endpoint": "https://serpapi.com/searches/fa5c1562366c4687/670a2f6ba775f2c583499ec8.json",
    "created_at": "2024-10-12 08:12:27 UTC",
    "processed_at": "2024-10-12 08:12:27 UTC",
    "google_url": "https://www.google.com/search?q=marzipan&oq=marzipan&uule=w+CAIQICIaQXVzdGluLFRleGFzLFVuaXRlZCBTdGF0ZXM&hl=en&gl=us&sourceid=chrome&ie=UTF-8",
    "raw_html_file": "https://serpapi.com/searches/fa5c1562366c4687/670a2f6ba775f2c583499ec8.html",
    "total_time_taken": 1.09
  },
  "search_parameters": {
    "engine": "google",
    "q": "marzipan",
    "location_requested": "Austin,Texas,United States",
    "location_used": "Austin,Texas,United States",
    "google_domain": "google.com",
    "hl": "en",
    "gl": "us",
    "device": "desktop"
  },
  "search_information": {
    "query_displayed": "marzipan",
    "total_results": 18400000,
    "time_taken_displayed": 0.32,
    "organic_results_state": "Results for exact spelling"
  },
  "recipes_results": [
    {
      "title": "Homemade Marzipan Recipe",
      "link": "https://elavegan.com/homemade-marzipan-recipe/",
      "source": "Elavegan",
      "rating": 5.0,
      "reviews": 91,
      "total_time": "5 min",
      "ingredients": [
        "Almond flour",
        "rose water",
        "almond extract",
        "powdered sugar"
      ],
      "thumbnail": "https://encrypted-tbn0.gstatic.com/images?q=tbn:ANd9GcTjdiwS_XnfEEKzBCfgCT6ZyKyNaO5bDB7t6zmqbq6zpjlTrqL-JzihFo8&s"
    },
    {
      "title": "Easy Marzipan",
      "link": "https://www.allrecipes.com/recipe/7740/marzipan/",
      "source": "Allrecipes",
      "rating": 4.5,
      "reviews": 15,
      "total_time": "24 hr 30 min",
      "ingredients": [
        "Egg whites",
        "almond extract",
        "sugar",
        "blanched almonds"
      ],
      "thumbnail": "https://encrypted-tbn0.gstatic.com/images?q=tbn:ANd9GcRTPN3cada252hD25vEjnEOvmnyJifagDmNAN3U3CgJallEeQ3G7h7SUitQ&s"
    },
    {
      "title": "Homemade Marzipan (Almond Paste)",
      "link": "https://www.daringgourmet.com/how-to-make-marzipan-almond-paste/",
      "source": "The Daring Gourmet",
      "rating": 4.9,
      "reviews": 430,
      "total_time": "5 min",
      "ingredients": [
        "Almond flour",
        "sugar free",
        "rose water",
        "corn syrup",
        "almond extract"
      ],
      "thumbnail": "https://encrypted-tbn0.gstatic.com/images?q=tbn:ANd9GcSaY9iSVKpODxMn9yTac5LrKlzO-fIHPMt1kOXcEPBvIUZ5ag8qwaRc7PES&s"
    }
  ],
  "knowledge_graph": {
    "title": "Marzipan",
    "type": "Confection",
    "entity_type": "food, foods_and_dishes",
    "kgmid": "/m/02bh6d",
    "knowledge_graph_search_link": "https://www.google.com/search?kgmid=/m/02bh6d&hl=en-US&q=Marzipan",
    "serpapi_knowledge_graph_search_link": "https://serpapi.com/search.json?device=desktop&engine=google&gl=us&google_domain=google.com&hl=en-US&kgmid=%2Fm%2F02bh6d&location=Austin%2CTexas%2CUnited+States&q=Marzipan",
    "header_images": [
      {
        "image": "https://serpapi.com/searches/670a2f6ba775f2c583499ec8/images/0abe5d4fc86630dbac49929236fd81435366c8c89a02f643daa4c3d0fa95e1f9a7dfd11c1436813a.jpeg",
        "source": "https://elavegan.com/homemade-marzipan-recipe/"
      },
      {
        "image": "https://serpapi.com/searches/670a2f6ba775f2c583499ec8/images/0abe5d4fc86630dbac49929236fd81435366c8c89a02f6435a8486b1ceaa6f796614ad4ce5a8662a.jpeg",
        "source": "https://lazyhomecook.com/marzipan-recipe/"
      },
      {
        "image": "https://serpapi.com/searches/670a2f6ba775f2c583499ec8/images/0abe5d4fc86630dbac49929236fd81435366c8c89a02f643b1c91ea8336c860deb0b62624051d496.jpeg",
        "source": "https://www.foodnetwork.com/how-to/packages/food-network-essentials/what-is-marzipan"
      },
      {
        "image": "https://serpapi.com/searches/670a2f6ba775f2c583499ec8/images/0abe5d4fc86630dbac49929236fd81435366c8c89a02f6438d09fe5ad6cbfb878c2977bad1314508.jpeg",
        "source": "https://www.withspice.com/blog/marzipan/"
      },
      {
        "image": "https://serpapi.com/searches/670a2f6ba775f2c583499ec8/images/0abe5d4fc86630dbac49929236fd81435366c8c89a02f643c1b5089b28167deac12671179d984ae7.jpeg",
        "source": "https://www.baking4happiness.com/how-to-make-marzipan.html"
      },
      {
        "image": "https://serpapi.com/searches/670a2f6ba775f2c583499ec8/images/0abe5d4fc86630dbac49929236fd81435366c8c89a02f643f2201a09e8155be9a6452b0f849584da.jpeg",
        "source": "https://www.withspice.com/blog/chocolate-covered-marzipan/"
      },
      {
        "image": "https://serpapi.com/searches/670a2f6ba775f2c583499ec8/images/0abe5d4fc86630dbac49929236fd81435366c8c89a02f643ba6251f39dacc09f5c7874e864e3f11b.jpeg",
        "source": "https://therecipecritic.com/marzipan/"
      },
      {
        "image": "https://encrypted-tbn0.gstatic.com/images?q=tbn:ANd9GcTokfIjpgots4PmLFE_a_aPOF8xi35qGUtg8C0SL3B13Q&s",
        "source": "https://skandibaking.com/marcipan-almond-confection/"
      },
      {
        "image": "https://encrypted-tbn0.gstatic.com/images?q=tbn:ANd9GcROEgRYwvvyIha8A9_pfILhJUz5_kJQrvJCvzoLfzrCGA&s",
        "source": "https://sugarfreelondoner.com/keto-marzipan-sugar-free/"
      }
    ],
    "description": "Marzipan is a confection consisting primarily of sugar and almond meal, sometimes augmented with almond oil or extract. It is often made into sweets; common uses are chocolate-covered marzipan and small marzipan imitations of fruits and vegetables.",
    "source": {
      "name": "Wikipedia",
      "link": "https://en.wikipedia.org/wiki/Marzipan"
    },
    "main_ingredients": "Almond meal, Sugar",
    "main_ingredients_links": [
      {
        "text": "Almond meal",
        "link": "https://www.google.com/search?sca_esv=8568a6baa21243e5&hl=en&gl=us&q=Almond+meal&si=ACC90nzx_D3_zUKRnpAjmO0UBLNxnt7EyN4YYdru6U3bxLI-L1yD7gHqut7gGhMPtawpHyDwrvy7wRfFD61X0D07h3hXCglcBLnVO_BvKhcL4mOiJrzJazso9g2Hu0v65gwqUP9JIER1IKc7tpxg0zQuFadjHJwsA-Fgs1GizOhrWDA67duNrtZLA5puzp1LF9K3KeQ7XAMBRbA3jn0qOxXypr70c_FFNhiOkZs44mKRhMd7-wNuRjQikJ57_QtEUFLI7wLqENcToDqKFN4lUFKFpFnqYr_M0Q%3D%3D&sa=X&ved=2ahUKEwinlvfQsoiJAxWeF2IAHVDxEO8QmxMoAHoECDkQAg"
      },
      {
        "text": "Sugar",
        "link": "https://www.google.com/search?sca_esv=8568a6baa21243e5&hl=en&gl=us&q=Sugar&si=ACC90nyvvWro6QmnyY1IfSdgk5wwjB1r8BGd_IWRjXqmKPQqmy218ctyIXQ8IIVZ4mtiF0oh0tvg6xFLxXu8q7wTa0FH2j84o3GmZDufjqaYsh1oAEYt4MlBvbqwWuEUmKdSag1CHlunoC7Mue2evf4AHGG2OWRku1Ipe3LkFGG0GGXd8KOYuc5Uj4q3TjDQzGU29hakRuogtUZsipPvkQsZ64MXI10UiJ5c-zqsU6NQ-fVq8uYBaNy3USCPJYGq14XEU_osoXWihv-o7PL57rr7KhxlbzPpcA%3D%3D&sa=X&ved=2ahUKEwinlvfQsoiJAxWeF2IAHVDxEO8QmxMoAXoECDkQAw"
      }
    ],
    "origins": "Germany, Spain, Italy",
    "origins_links": [
      {
        "text": "Germany",
        "link": "https://www.google.com/search?sca_esv=8568a6baa21243e5&hl=en&gl=us&q=Germany&si=ACC90nyvvWro6QmnyY1IfSdgk5wwjB1r8BGd_IWRjXqmKPQqm5xAoc4Or3_lNVhz0B-ZY1dh6r4Hwa8DhchjePAaIS3JFmV60aSIUPt6nuvC9OuiP4FGLZ6CJnoVRZgSJKEtb4tTbvhd8nJLkxXKAS4cAtNQzwHM-qKKKN9lGp3Sd4HQPtwb2ZROy43Sd4-e6ll21dWHzIou8dKzQjxNHqtnKJQny8bMlqczF1OpcXH__RanAmRrdjg8mzgmOTBOIk-6XQpXc928-Y9ynEgedR85bctRa-cCNQ%3D%3D&sa=X&ved=2ahUKEwinlvfQsoiJAxWeF2IAHVDxEO8QmxMoAHoECDoQAg"
      },
      {
        "text": "Spain",
        "link": "https://www.google.com/search?sca_esv=8568a6baa21243e5&hl=en&gl=us&q=Spain&si=ACC90nyvvWro6QmnyY1IfSdgk5wwjB1r8BGd_IWRjXqmKPQqmwF3dMXOpWF4TqPuYxHsJOerC_kPhaOXrOFj9PyXgoGPzCPtYXnBPHCgwoqEVhOsPI4M8IKAeDPySf_MXLlC-8TuCq2hutdw_oJVRAKopEbSe_vt7Zhn4C7yj1A1oWYySQaUGw1Jj0p220M_t5ZJRP14W8XEjDtRAgRDvhsA1cFiYlnsNnrURZmuWFsCak8RjYQlA7i7JdQWOhNc1nY3OtgsQyZ0&sa=X&ved=2ahUKEwinlvfQsoiJAxWeF2IAHVDxEO8QmxMoAXoECDoQAw"
      },
      {
        "text": "Italy",
        "link": "https://www.google.com/search?sca_esv=8568a6baa21243e5&hl=en&gl=us&q=Italy&si=ACC90nyvvWro6QmnyY1IfSdgk5wwjB1r8BGd_IWRjXqmKPQqmx4usP0NcQYWgoFeN58VvULZhegOWKdDlsMcti4oOs9oMO-Q2nP66GBPi-suWNvOWFfDDXWRfWDpJ0-c5ilO6IK4_wkVNoO7UvjZFTel4C0QR8JGyFIy9Pm5Y1f8cUM_o-f7lAN7dIlbXt6vShUb93KjEGl_KUM1FIsH606ZsJv94OzN7XBPOWBdb1O5NScdu9UhTzxfR_K8LOzG2WcP4Vjz7o3v&sa=X&ved=2ahUKEwinlvfQsoiJAxWeF2IAHVDxEO8QmxMoAnoECDoQBA"
      }
    ],
    "alternative_names": "Marzapane, marchpane",
    "alternative_names_links": [
      {
        "text": "marchpane",
        "link": "https://www.google.com/search?sca_esv=8568a6baa21243e5&hl=en&gl=us&q=marchpane&stick=H4sIAAAAAAAAAONgVuLVT9c3NMxLzyjKzjUuWsTKmZtYlJxRkJiXCgC7JWFzHQAAAA&sa=X&ved=2ahUKEwinlvfQsoiJAxWeF2IAHVDxEO8QmxMoAHoECDYQAg"
      }
    ],
    "people_also_search_for": [
      {
        "name": "Mascarpone",
        "link": "https://www.google.com/search?sca_esv=8568a6baa21243e5&hl=en&gl=us&si=ACC90nzx_D3_zUKRnpAjmO0UBLNxnt7EyN4YYdru6U3bxLI-L2ltM4-PEjBwptUUW-y_sX60x6lxoJzRz1CTzY18bpBmOe57PtonTpwyar8XTgQvPZzo2Oc4m7-tjIkzQ75_QbeGhdO0uo-KpPHd3bQGZNTRFL90tM_oKbnp9xjv7V566KsG0XFaNE_9nPxrgAt0d4FbwWOZE4FhdtIrxssc1JZ7MbajTYOf7CflrQkeQOu3WiDTYLJktYyY35jpOwAizJD31yJvEtt8ITgYsSBjXwlV3-j-WhrNPJzp0NypTJt9gI6idx8%3D&q=Mascarpone&sa=X&ved=2ahUKEwinlvfQsoiJAxWeF2IAHVDxEO8Qs9oBKAB6BAg3EAU",
        "serpapi_link": "https://serpapi.com/search.json?device=desktop&engine=google&gl=us&google_domain=google.com&hl=en&location=Austin%2CTexas%2CUnited+States&q=Mascarpone&si=ACC90nzx_D3_zUKRnpAjmO0UBLNxnt7EyN4YYdru6U3bxLI-L2ltM4-PEjBwptUUW-y_sX60x6lxoJzRz1CTzY18bpBmOe57PtonTpwyar8XTgQvPZzo2Oc4m7-tjIkzQ75_QbeGhdO0uo-KpPHd3bQGZNTRFL90tM_oKbnp9xjv7V566KsG0XFaNE_9nPxrgAt0d4FbwWOZE4FhdtIrxssc1JZ7MbajTYOf7CflrQkeQOu3WiDTYLJktYyY35jpOwAizJD31yJvEtt8ITgYsSBjXwlV3-j-WhrNPJzp0NypTJt9gI6idx8%3D",
        "image": "https://serpapi.com/searches/670a2f6ba775f2c583499ec8/images/0abe5d4fc86630dbac49929236fd81436209ac0e0fdac1f79d54d68d5014a1e3d274e704a6725efc5874bba056c69ebb.jpeg"
      },
      {
        "name": "Nougat",
        "link": "https://www.google.com/search?sca_esv=8568a6baa21243e5&hl=en&gl=us&si=ACC90nzx_D3_zUKRnpAjmO0UBLNxnt7EyN4YYdru6U3bxLI-L5kHx8tv8E084Rjh2_7DWwZDoDdQM6-dkXz4_VwhfK7m84TcSk8Y_QMsyxEAf5VfJt9k8uw6vJBqFCrWNQMEK-AvIIbiQTjCwDPWwoG6NDc19TO2xD4pZyYHhSIDETirbLvlv7PqUyjbY2EVLE7ZWaX9OmiMWmm8guCoanghMt8gTUtbcIAOkF4Mtgmnm8D1MoO0V25LpcQ8vRV8-d-pXKRxIDsPYyWUo-dzUIdPOa_imXXd0uroRrcne8Gr8WOcueh2LH0%3D&q=Nougat&sa=X&ved=2ahUKEwinlvfQsoiJAxWeF2IAHVDxEO8Qs9oBKAB6BAg3EAk",
        "serpapi_link": "https://serpapi.com/search.json?device=desktop&engine=google&gl=us&google_domain=google.com&hl=en&location=Austin%2CTexas%2CUnited+States&q=Nougat&si=ACC90nzx_D3_zUKRnpAjmO0UBLNxnt7EyN4YYdru6U3bxLI-L5kHx8tv8E084Rjh2_7DWwZDoDdQM6-dkXz4_VwhfK7m84TcSk8Y_QMsyxEAf5VfJt9k8uw6vJBqFCrWNQMEK-AvIIbiQTjCwDPWwoG6NDc19TO2xD4pZyYHhSIDETirbLvlv7PqUyjbY2EVLE7ZWaX9OmiMWmm8guCoanghMt8gTUtbcIAOkF4Mtgmnm8D1MoO0V25LpcQ8vRV8-d-pXKRxIDsPYyWUo-dzUIdPOa_imXXd0uroRrcne8Gr8WOcueh2LH0%3D",
        "image": "https://serpapi.com/searches/670a2f6ba775f2c583499ec8/images/0abe5d4fc86630dbac49929236fd81436209ac0e0fdac1f79d54d68d5014a1e3350a068df39f27bc6c3f8c1712751788.jpeg"
      },
      {
        "name": "Fondant icing",
        "link": "https://www.google.com/search?sca_esv=8568a6baa21243e5&hl=en&gl=us&si=ACC90nzx_D3_zUKRnpAjmO0UBLNxnt7EyN4YYdru6U3bxLI-L-1Yi7k323F635kfsDo2UcVgSC2VljdMgAa5w7L01VbyhiZ3jN7gySNUf6Uz0YSQD7BBWs4_P6zJCneyH4v9vs5V579_NvxUx-QOl7MN2jX2vcChwVkUlGStiwHF-sEdJf-eB0rma2p3RaMt_sV6MMI62pBbK3HfHbPU3usZ8od3A-zmWxycZoBvwh1JMEZK0S6blWiQiPFsDfSMsd54kAZteWTbJQu0lKZuHUatbaXk4TX8cC0edtHwK7sjSSqK9c_abf0%3D&q=Fondant&sa=X&ved=2ahUKEwinlvfQsoiJAxWeF2IAHVDxEO8Qs9oBKAB6BAg3EA0",
        "serpapi_link": "https://serpapi.com/search.json?device=desktop&engine=google&gl=us&google_domain=google.com&hl=en&location=Austin%2CTexas%2CUnited+States&q=Fondant&si=ACC90nzx_D3_zUKRnpAjmO0UBLNxnt7EyN4YYdru6U3bxLI-L-1Yi7k323F635kfsDo2UcVgSC2VljdMgAa5w7L01VbyhiZ3jN7gySNUf6Uz0YSQD7BBWs4_P6zJCneyH4v9vs5V579_NvxUx-QOl7MN2jX2vcChwVkUlGStiwHF-sEdJf-eB0rma2p3RaMt_sV6MMI62pBbK3HfHbPU3usZ8od3A-zmWxycZoBvwh1JMEZK0S6blWiQiPFsDfSMsd54kAZteWTbJQu0lKZuHUatbaXk4TX8cC0edtHwK7sjSSqK9c_abf0%3D",
        "image": "https://serpapi.com/searches/670a2f6ba775f2c583499ec8/images/0abe5d4fc86630dbac49929236fd81436209ac0e0fdac1f79d54d68d5014a1e304e64229bb876b3829bb78a31dc04a19.jpeg"
      },
      {
        "name": "Polvor\u00f3n",
        "link": "https://www.google.com/search?sca_esv=8568a6baa21243e5&hl=en&gl=us&si=ACC90ny8E30vD16OoPAAI4cStfcliGy35W8UAhb0TsHNc_ISQWOpgenWlPw01114kVzkTXj0nec9urii2l_Bku-ycW3YAxszenby8ntj5cJl2sKnCvKrnsvo6iaJ-VrJH0DiNaRA6tj8SKgIRqLcQ-OJaeVQl0-XeQMEubmvmun5v6RY_v5x7NOHlf4yU7ygNIsguG2QVaar-6qNFXkKJj0wAisKiW7rD3huv5GYkkgfSEj5C_Vtm1-jHU1OgdO6Rdu8IU9bqb9g95S6C7eUKd42PNz4AjGygcW_18HsFwTLNWXCsl5EQuc%3D&q=Polvor%C3%B3n&sa=X&ved=2ahUKEwinlvfQsoiJAxWeF2IAHVDxEO8Qs9oBKAB6BAg3EBE",
        "serpapi_link": "https://serpapi.com/search.json?device=desktop&engine=google&gl=us&google_domain=google.com&hl=en&location=Austin%2CTexas%2CUnited+States&q=Polvor%C3%B3n&si=ACC90ny8E30vD16OoPAAI4cStfcliGy35W8UAhb0TsHNc_ISQWOpgenWlPw01114kVzkTXj0nec9urii2l_Bku-ycW3YAxszenby8ntj5cJl2sKnCvKrnsvo6iaJ-VrJH0DiNaRA6tj8SKgIRqLcQ-OJaeVQl0-XeQMEubmvmun5v6RY_v5x7NOHlf4yU7ygNIsguG2QVaar-6qNFXkKJj0wAisKiW7rD3huv5GYkkgfSEj5C_Vtm1-jHU1OgdO6Rdu8IU9bqb9g95S6C7eUKd42PNz4AjGygcW_18HsFwTLNWXCsl5EQuc%3D",
        "image": "https://serpapi.com/searches/670a2f6ba775f2c583499ec8/images/0abe5d4fc86630dbac49929236fd81436209ac0e0fdac1f79d54d68d5014a1e3ef7c60d90d368d8450e81183fb506015.jpeg"
      }
    ]
  },
  "inline_images": [
    {
      "link": "https://www.google.com/search?q=marzipan&sca_esv=8568a6baa21243e5&hl=en&gl=us&udm=2&source=iu&ictx=1&vet=1&fir=_fABc7lzQyAH0M%252CJvdoa2uc-gDeAM%252C%252Fm%252F02bh6d%253BTGTu9Vc-xjwykM%252CMwp9PrvRY3SXkM%252C_%253BQOqm4-w-ecpy_M%252CIOzHtzIX4n82MM%252C_%253B4RkrAFheo2cwIM%252C2EWvNt4P3ed1mM%252C_%253BVfCgGUY_Aiiw_M%252Cw0vXVvC4ehyfuM%252C_%253BLFEvlbVxicc-cM%252C2cKJqWeBORUP_M%252C_%253B3_TsavTqZ_-hiM%252CNrpe_1XHeppGGM%252C_%253BsTKf0MI8EET9mM%252Cj-xM_ojwFl1cvM%252C_%253BqPPov4aAQOSHKM%252CKBGSi9eySVslcM%252C_&usg=AI4_-kTfeJZc61GhamhmQSguL-nE6o2yCQ&sa=X&ved=2ahUKEwinlvfQsoiJAxWeF2IAHVDxEO8Q_B16BAg9EAE#vhid=_fABc7lzQyAH0M&vssid=mosaic",
      "source": "https://elavegan.com/homemade-marzipan-recipe/",
      "thumbnail": "https://serpapi.com/searches/670a2f6ba775f2c583499ec8/images/523fe40d375e01f28b3c187d42e2e4a6ebc74888c1a1b2dc470368814ed6913d.jpeg",
      "original": "https://elavegan.com/wp-content/uploads/2019/12/eggless-homemade-marzipan-with-blanched-almonds.jpg",
      "title": "elavegan.com/wp-content/uploads/2019/12/eggless-ho...",
      "source_name": "elavegan.com"
    },
    {
      "link": "https://www.google.com/search?q=marzipan&sca_esv=8568a6baa21243e5&hl=en&gl=us&udm=2&source=iu&ictx=1&vet=1&fir=_fABc7lzQyAH0M%252CJvdoa2uc-gDeAM%252C_%253BTGTu9Vc-xjwykM%252CMwp9PrvRY3SXkM%252C_%253BQOqm4-w-ecpy_M%252CIOzHtzIX4n82MM%252C_%253B4RkrAFheo2cwIM%252C2EWvNt4P3ed1mM%252C_%253BVfCgGUY_Aiiw_M%252Cw0vXVvC4ehyfuM%252C_%253BLFEvlbVxicc-cM%252C2cKJqWeBORUP_M%252C_%253B3_TsavTqZ_-hiM%252CNrpe_1XHeppGGM%252C_%253BsTKf0MI8EET9mM%252Cj-xM_ojwFl1cvM%252C_%253BqPPov4aAQOSHKM%252CKBGSi9eySVslcM%252C_&usg=AI4_-kRrhWwgMMwp0BPJQO9iTXAd0az9iA&sa=X&ved=2ahUKEwinlvfQsoiJAxWeF2IAHVDxEO8Q_h16BAhFEAE#vhid=TGTu9Vc-xjwykM&vssid=mosaic",
      "source": "https://lazyhomecook.com/marzipan-recipe/",
      "thumbnail": "https://serpapi.com/searches/670a2f6ba775f2c583499ec8/images/523fe40d375e01f2259564f07a2b6d241f412541565250a5aba6e76e8c5ecd43.jpeg",
      "original": "https://lazyhomecook.com/wp-content/uploads/2020/06/IMG_20200615_114744034-scaled-720x720.jpg",
      "title": "Marzipan recipe",
      "source_name": "Lazyhomecook"
    },
    {
      "link": "https://www.google.com/search?q=marzipan&sca_esv=8568a6baa21243e5&hl=en&gl=us&udm=2&source=iu&ictx=1&vet=1&fir=_fABc7lzQyAH0M%252CJvdoa2uc-gDeAM%252C_%253BTGTu9Vc-xjwykM%252CMwp9PrvRY3SXkM%252C_%253BQOqm4-w-ecpy_M%252CIOzHtzIX4n82MM%252C_%253B4RkrAFheo2cwIM%252C2EWvNt4P3ed1mM%252C_%253BVfCgGUY_Aiiw_M%252Cw0vXVvC4ehyfuM%252C_%253BLFEvlbVxicc-cM%252C2cKJqWeBORUP_M%252C_%253B3_TsavTqZ_-hiM%252CNrpe_1XHeppGGM%252C_%253BsTKf0MI8EET9mM%252Cj-xM_ojwFl1cvM%252C_%253BqPPov4aAQOSHKM%252CKBGSi9eySVslcM%252C_&usg=AI4_-kRrhWwgMMwp0BPJQO9iTXAd0az9iA&sa=X&ved=2ahUKEwinlvfQsoiJAxWeF2IAHVDxEO8Q_h16BAhHEAE#vhid=QOqm4-w-ecpy_M&vssid=mosaic",
      "source": "https://www.foodnetwork.com/how-to/packages/food-network-essentials/what-is-marzipan",
      "thumbnail": "https://serpapi.com/searches/670a2f6ba775f2c583499ec8/images/523fe40d375e01f267fb006089e004e59ae89a7692261d5e8e56608d352cafec.jpeg",
      "original": "https://food.fnr.sndimg.com/content/dam/images/food/fullset/2021/11/22/marzipan-fruit-cake.jpg.rend.hgtvcom.1280.960.suffix/1637613792462.jpeg",
      "title": "What Is Marzipan? | Cooking School | Food Network",
      "source_name": "Food Network"
    },
    {
      "link": "https://www.google.com/search?q=marzipan&sca_esv=8568a6baa21243e5&hl=en&gl=us&udm=2&source=iu&ictx=1&vet=1&fir=_fABc7lzQyAH0M%252CJvdoa2uc-gDeAM%252C_%253BTGTu9Vc-xjwykM%252CMwp9PrvRY3SXkM%252C_%253BQOqm4-w-ecpy_M%252CIOzHtzIX4n82MM%252C_%253B4RkrAFheo2cwIM%252C2EWvNt4P3ed1mM%252C_%253BVfCgGUY_Aiiw_M%252Cw0vXVvC4ehyfuM%252C_%253BLFEvlbVxicc-cM%252C2cKJqWeBORUP_M%252C_%253B3_TsavTqZ_-hiM%252CNrpe_1XHeppGGM%252C_%253BsTKf0MI8EET9mM%252Cj-xM_ojwFl1cvM%252C_%253BqPPov4aAQOSHKM%252CKBGSi9eySVslcM%252C_&usg=AI4_-kRrhWwgMMwp0BPJQO9iTXAd0az9iA&sa=X&ved=2ahUKEwinlvfQsoiJAxWeF2IAHVDxEO8Q_h16BAhIEAE#vhid=4RkrAFheo2cwIM&vssid=mosaic",
      "source": "https://www.withspice.com/blog/marzipan/",
      "thumbnail": "https://serpapi.com/searches/670a2f6ba775f2c583499ec8/images/523fe40d375e01f2354645129fe6020bc21fc8e9bf8fee91e0c932b517ac16d8.jpeg",
      "original": "https://www.withspice.com/wp-content/uploads/2023/10/marzipan.jpg",
      "title": "how to make marzipan",
      "source_name": "With Spice"
    },
    {
      "link": "https://www.google.com/search?q=marzipan&sca_esv=8568a6baa21243e5&hl=en&gl=us&udm=2&source=iu&ictx=1&vet=1&fir=_fABc7lzQyAH0M%252CJvdoa2uc-gDeAM%252C_%253BTGTu9Vc-xjwykM%252CMwp9PrvRY3SXkM%252C_%253BQOqm4-w-ecpy_M%252CIOzHtzIX4n82MM%252C_%253B4RkrAFheo2cwIM%252C2EWvNt4P3ed1mM%252C_%253BVfCgGUY_Aiiw_M%252Cw0vXVvC4ehyfuM%252C_%253BLFEvlbVxicc-cM%252C2cKJqWeBORUP_M%252C_%253B3_TsavTqZ_-hiM%252CNrpe_1XHeppGGM%252C_%253BsTKf0MI8EET9mM%252Cj-xM_ojwFl1cvM%252C_%253BqPPov4aAQOSHKM%252CKBGSi9eySVslcM%252C_&usg=AI4_-kRrhWwgMMwp0BPJQO9iTXAd0az9iA&sa=X&ved=2ahUKEwinlvfQsoiJAxWeF2IAHVDxEO8Q_h16BAhEEAE#vhid=VfCgGUY_Aiiw_M&vssid=mosaic",
      "source": "https://www.baking4happiness.com/how-to-make-marzipan.html",
      "thumbnail": "https://serpapi.com/searches/670a2f6ba775f2c583499ec8/images/523fe40d375e01f2da56e3489e3c0851dddc9fea7238b0cd7009039b911369a8.jpeg",
      "original": "https://www.baking4happiness.com/wp-content/uploads/2020/10/Making-marzipan-paste-yourself.jpg",
      "title": "How to make Marzipan at home",
      "source_name": "Baking for Happiness"
    },
    {
      "link": "https://www.google.com/search?q=marzipan&sca_esv=8568a6baa21243e5&hl=en&gl=us&udm=2&source=iu&ictx=1&vet=1&fir=_fABc7lzQyAH0M%252CJvdoa2uc-gDeAM%252C_%253BTGTu9Vc-xjwykM%252CMwp9PrvRY3SXkM%252C_%253BQOqm4-w-ecpy_M%252CIOzHtzIX4n82MM%252C_%253B4RkrAFheo2cwIM%252C2EWvNt4P3ed1mM%252C_%253BVfCgGUY_Aiiw_M%252Cw0vXVvC4ehyfuM%252C_%253BLFEvlbVxicc-cM%252C2cKJqWeBORUP_M%252C_%253B3_TsavTqZ_-hiM%252CNrpe_1XHeppGGM%252C_%253BsTKf0MI8EET9mM%252Cj-xM_ojwFl1cvM%252C_%253BqPPov4aAQOSHKM%252CKBGSi9eySVslcM%252C_&usg=AI4_-kRrhWwgMMwp0BPJQO9iTXAd0az9iA&sa=X&ved=2ahUKEwinlvfQsoiJAxWeF2IAHVDxEO8Q_h16BAhCEAE#vhid=LFEvlbVxicc-cM&vssid=mosaic",
      "source": "https://www.withspice.com/blog/chocolate-covered-marzipan/",
      "thumbnail": "https://serpapi.com/searches/670a2f6ba775f2c583499ec8/images/523fe40d375e01f245f97aa2268c16e3305b2b82e7a912c483ad669b9f57ce84.jpeg",
      "original": "https://www.withspice.com/wp-content/uploads/2023/10/marzipan-chocolate.jpg",
      "title": "chocolate covered marzipan",
      "source_name": "With Spice"
    },
    {
      "link": "https://www.google.com/search?q=marzipan&sca_esv=8568a6baa21243e5&hl=en&gl=us&udm=2&source=iu&ictx=1&vet=1&fir=_fABc7lzQyAH0M%252CJvdoa2uc-gDeAM%252C_%253BTGTu9Vc-xjwykM%252CMwp9PrvRY3SXkM%252C_%253BQOqm4-w-ecpy_M%252CIOzHtzIX4n82MM%252C_%253B4RkrAFheo2cwIM%252C2EWvNt4P3ed1mM%252C_%253BVfCgGUY_Aiiw_M%252Cw0vXVvC4ehyfuM%252C_%253BLFEvlbVxicc-cM%252C2cKJqWeBORUP_M%252C_%253B3_TsavTqZ_-hiM%252CNrpe_1XHeppGGM%252C_%253BsTKf0MI8EET9mM%252Cj-xM_ojwFl1cvM%252C_%253BqPPov4aAQOSHKM%252CKBGSi9eySVslcM%252C_&usg=AI4_-kRrhWwgMMwp0BPJQO9iTXAd0az9iA&sa=X&ved=2ahUKEwinlvfQsoiJAxWeF2IAHVDxEO8Q_h16BAhBEAE#vhid=3_TsavTqZ_-hiM&vssid=mosaic",
      "source": "https://therecipecritic.com/marzipan/",
      "thumbnail": "https://serpapi.com/searches/670a2f6ba775f2c583499ec8/images/523fe40d375e01f266d95c803773616c855a87f576bb74f60f3c106cab43d11e.jpeg",
      "original": "https://therecipecritic.com/wp-content/uploads/2023/02/marzipan-1.jpg",
      "title": "Marzipan",
      "source_name": "The Recipe Critic"
    },
    {
      "link": "https://www.google.com/search?q=marzipan&sca_esv=8568a6baa21243e5&hl=en&gl=us&udm=2&source=iu&ictx=1&vet=1&fir=_fABc7lzQyAH0M%252CJvdoa2uc-gDeAM%252C_%253BTGTu9Vc-xjwykM%252CMwp9PrvRY3SXkM%252C_%253BQOqm4-w-ecpy_M%252CIOzHtzIX4n82MM%252C_%253B4RkrAFheo2cwIM%252C2EWvNt4P3ed1mM%252C_%253BVfCgGUY_Aiiw_M%252Cw0vXVvC4ehyfuM%252C_%253BLFEvlbVxicc-cM%252C2cKJqWeBORUP_M%252C_%253B3_TsavTqZ_-hiM%252CNrpe_1XHeppGGM%252C_%253BsTKf0MI8EET9mM%252Cj-xM_ojwFl1cvM%252C_%253BqPPov4aAQOSHKM%252CKBGSi9eySVslcM%252C_&usg=AI4_-kRrhWwgMMwp0BPJQO9iTXAd0az9iA&sa=X&ved=2ahUKEwinlvfQsoiJAxWeF2IAHVDxEO8Q_h16BAg-EAE#vhid=sTKf0MI8EET9mM&vssid=mosaic",
      "source": "https://skandibaking.com/marcipan-almond-confection/",
      "thumbnail": "https://encrypted-tbn0.gstatic.com/images?q=tbn:ANd9GcTokfIjpgots4PmLFE_a_aPOF8xi35qGUtg8C0SL3B13Q&s",
      "original": "https://skandibaking.com/wp-content/uploads/2020/09/DSC_0491.jpg",
      "title": "Marcipan (Almond Confection)",
      "source_name": "Skandibaking"
    },
    {
      "link": "https://www.google.com/search?q=marzipan&sca_esv=8568a6baa21243e5&hl=en&gl=us&udm=2&source=iu&ictx=1&vet=1&fir=_fABc7lzQyAH0M%252CJvdoa2uc-gDeAM%252C_%253BTGTu9Vc-xjwykM%252CMwp9PrvRY3SXkM%252C_%253BQOqm4-w-ecpy_M%252CIOzHtzIX4n82MM%252C_%253B4RkrAFheo2cwIM%252C2EWvNt4P3ed1mM%252C_%253BVfCgGUY_Aiiw_M%252Cw0vXVvC4ehyfuM%252C_%253BLFEvlbVxicc-cM%252C2cKJqWeBORUP_M%252C_%253B3_TsavTqZ_-hiM%252CNrpe_1XHeppGGM%252C_%253BsTKf0MI8EET9mM%252Cj-xM_ojwFl1cvM%252C_%253BqPPov4aAQOSHKM%252CKBGSi9eySVslcM%252C_&usg=AI4_-kRrhWwgMMwp0BPJQO9iTXAd0az9iA&sa=X&ved=2ahUKEwinlvfQsoiJAxWeF2IAHVDxEO8Q_h16BAhGEAE#vhid=qPPov4aAQOSHKM&vssid=mosaic",
      "source": "https://sugarfreelondoner.com/keto-marzipan-sugar-free/",
      "thumbnail": "https://encrypted-tbn0.gstatic.com/images?q=tbn:ANd9GcROEgRYwvvyIha8A9_pfILhJUz5_kJQrvJCvzoLfzrCGA&s",
      "original": "https://sugarfreelondoner.com/wp-content/uploads/2021/03/keto-marzipan-low-carb.jpg",
      "title": "Sugar Free Keto Marzipan",
      "source_name": "Sugar Free Londoner"
    }
  ],
  "inline_products": [
    {
      "position": 1,
      "title": "Odense Marzipan Almond Candy Dough",
      "block_title": "In stores nearby",
      "source": "H-E-B",
      "price": 5.17,
      "currency": "$",
      "rating": 5.0,
      "thumbnail": "https://encrypted-tbn0.gstatic.com/shopping?q=tbn:ANd9GcRjpq4s0HBqr60q4BhyZ6H2t9OFD-1rPTzA-eSsfYfC7XlsR4ob_po3q-xNgQNFseOdTS5c6iQv"
    },
    {
      "position": 2,
      "title": "Niederegger Chocolate Covered Marzipan Loaf",
      "block_title": "In stores nearby",
      "tag": "20% OFF",
      "source": "World Market",
      "price": 5.59,
      "currency": "$",
      "original_price": 7,
      "rating": 4.6,
      "thumbnail": "https://encrypted-tbn2.gstatic.com/shopping?q=tbn:ANd9GcTi-Qq9bb1TRRzLM8ojhUwaSzCpTSytzcjm-gTba0f0ui9yPl-lAUoG3MwDTU-c6qXBPHbLco1t"
    },
    {
      "position": 3,
      "title": "World Market Odenwaelder Marzipan Mixed Fruit 8 Piece",
      "block_title": "In stores nearby",
      "tag": "20% OFF",
      "source": "World Market",
      "price": 8.79,
      "currency": "$",
      "original_price": 11,
      "rating": 3.7,
      "thumbnail": "https://encrypted-tbn1.gstatic.com/shopping?q=tbn:ANd9GcSFd2LOgFrv3WT3fOtUr85mFdl_0PaJIJJ-A8cMl_iVbAxauES6vD3V5824uLQfU3W4-VWr4jE"
    },
    {
      "position": 4,
      "title": "World Market Mirabell Mozart Marzipan Gift Box",
      "block_title": "In stores nearby",
      "tag": "20% OFF",
      "source": "World Market",
      "price": 13.59,
      "currency": "$",
      "original_price": 17,
      "rating": 3.6,
      "thumbnail": "https://encrypted-tbn2.gstatic.com/shopping?q=tbn:ANd9GcS7Vk8PORWXRJpjAIu42OWZOAFjztOW61dx0h-ypO5hBsTlGbz6OLz-zAzbDjEQ21N-n8Pt9Eo-"
    },
    {
      "position": 5,
      "title": "Schlunder Marzipan Stollen Bites by World Market",
      "block_title": "In stores nearby",
      "tag": "20% OFF",
      "source": "World Market",
      "price": 7.99,
      "currency": "$",
      "original_price": 10,
      "rating": 4.5,
      "thumbnail": "https://encrypted-tbn2.gstatic.com/shopping?q=tbn:ANd9GcRhEpKyN62KjlQ1uzsCxyeBD8jKuUda_QX1_iJjtv5QQ9o4PxkTt0Vbwp15cm5wjQu27Y75FYf6"
    }
  ],
  "immersive_products": [
    {
      "category": "Popular products",
      "thumbnail": "https://serpapi.com/searches/670a2f6ba775f2c583499ec8/images/5196beefa97782983066e01e9f28f30f23b011ffabba38b7d819f4de17415e5f.jpeg",
      "source_logo": "https://serpapi.com/searches/670a2f6ba775f2c583499ec8/images/5196beefa97782983066e01e9f28f30fac38b91d102d40a36d81157fa2e16efe1667bbea12175a39.png",
      "source": "Amazon.com - Seller",
      "title": "Bergen Marzipan Fruit Assorted Basket",
      "rating": 4.4,
      "reviews": 43,
      "price": "$7.56",
      "extracted_price": 7.56,
      "original_price": "$8",
      "extracted_original_price": 8,
      "extensions": [
        "5% OFF"
      ],
      "immersive_product_page_token": "eyJlaSI6ImJDOEtaNmV3RUo2dmlMTVAwT0xELUE0IiwicHJvZHVjdGlkIjoiIiwiY2F0YWxvZ2lkIjoiMTMxOTI4NDEwNjgxNjkwNDc0OSIsInZjIjoiIiwidnNjIjoiIiwiaGVhZGxpbmVPZmZlckRvY2lkIjoiMTY5MjEwMTIxMjQ4MzAyOTc4MTUiLCJpbWFnZURvY2lkIjoiMTU1Mzk1ODU2MzA3NjI0OTIyNzgiLCJyZHMiOiJQQ18xMDkxMDUzMTI3NjY5MTcxMzQ1MXxQUk9EX1BDXzEwOTEwNTMxMjc2NjkxNzEzNDUxIiwicXVlcnkiOiJtYXJ6aXBhbiJ9",
      "serpapi_link": "https://serpapi.com/search.json?engine=google_immersive_product&page_token=eyJlaSI6ImJDOEtaNmV3RUo2dmlMTVAwT0xELUE0IiwicHJvZHVjdGlkIjoiIiwiY2F0YWxvZ2lkIjoiMTMxOTI4NDEwNjgxNjkwNDc0OSIsInZjIjoiIiwidnNjIjoiIiwiaGVhZGxpbmVPZmZlckRvY2lkIjoiMTY5MjEwMTIxMjQ4MzAyOTc4MTUiLCJpbWFnZURvY2lkIjoiMTU1Mzk1ODU2MzA3NjI0OTIyNzgiLCJyZHMiOiJQQ18xMDkxMDUzMTI3NjY5MTcxMzQ1MXxQUk9EX1BDXzEwOTEwNTMxMjc2NjkxNzEzNDUxIiwicXVlcnkiOiJtYXJ6aXBhbiJ9"
    },
    {
      "category": "Popular products",
      "thumbnail": "https://serpapi.com/searches/670a2f6ba775f2c583499ec8/images/5196beefa97782983066e01e9f28f30f887d4ad96350285dbee589572ebfa27b.jpeg",
      "source_logo": "https://serpapi.com/searches/670a2f6ba775f2c583499ec8/images/5196beefa97782983066e01e9f28f30fa5f6e4986de03f64dc7534a6d03b63a54f28033d5e93863e.png",
      "source": "H-E-B",
      "title": "Odense Marzipan Almond Candy Dough",
      "rating": 5.0,
      "reviews": 4,
      "price": "$5.17",
      "extracted_price": 5.17,
      "location": "10 mi \u00b7 In stock",
      "immersive_product_page_token": "eyJlaSI6ImJDOEtaNmV3RUo2dmlMTVAwT0xELUE0IiwicHJvZHVjdGlkIjoiIiwiY2F0YWxvZ2lkIjoiMjIzOTEwOTA3NzQ2NDU4MzUzIiwidmMiOiIiLCJ2c2MiOiIiLCJoZWFkbGluZU9mZmVyRG9jaWQiOiIxNjY0NjIxNzExNzM3MzU4NjczOSIsImltYWdlRG9jaWQiOiIxODQyOTgyMTA5NzA4MTUwMzk0OCIsInJkcyI6IlBDXzgwNzMzODk0Mzk2OTAzOTUzMTd8UFJPRF9QQ184MDczMzg5NDM5NjkwMzk1MzE3IiwicXVlcnkiOiJtYXJ6aXBhbiJ9",
      "serpapi_link": "https://serpapi.com/search.json?engine=google_immersive_product&page_token=eyJlaSI6ImJDOEtaNmV3RUo2dmlMTVAwT0xELUE0IiwicHJvZHVjdGlkIjoiIiwiY2F0YWxvZ2lkIjoiMjIzOTEwOTA3NzQ2NDU4MzUzIiwidmMiOiIiLCJ2c2MiOiIiLCJoZWFkbGluZU9mZmVyRG9jaWQiOiIxNjY0NjIxNzExNzM3MzU4NjczOSIsImltYWdlRG9jaWQiOiIxODQyOTgyMTA5NzA4MTUwMzk0OCIsInJkcyI6IlBDXzgwNzMzODk0Mzk2OTAzOTUzMTd8UFJPRF9QQ184MDczMzg5NDM5NjkwMzk1MzE3IiwicXVlcnkiOiJtYXJ6aXBhbiJ9"
    },
    {
      "category": "Popular products",
      "thumbnail": "https://serpapi.com/searches/670a2f6ba775f2c583499ec8/images/5196beefa97782983066e01e9f28f30fc087e41fba2ca6259411d19530c5121c.jpeg",
      "source_logo": "https://serpapi.com/searches/670a2f6ba775f2c583499ec8/images/5196beefa97782983066e01e9f28f30f383ad5c2b4041f9432406c407dbceea2e7f55de8d4b4c793.png",
      "source": "Brands of Germany",
      "title": "Niederegger Classic Marzipan Variations",
      "rating": 4.8,
      "reviews": 76,
      "price": "$19.60",
      "extracted_price": 19.6,
      "immersive_product_page_token": "eyJlaSI6ImJDOEtaNmV3RUo2dmlMTVAwT0xELUE0IiwicHJvZHVjdGlkIjoiIiwiY2F0YWxvZ2lkIjoiOTIxMTg3MDI2NjQ2OTAzMzQ5MiIsInZjIjoiIiwidnNjIjoiIiwiaGVhZGxpbmVPZmZlckRvY2lkIjoiMTc0OTg3MjM1OTU4MDYxMjg1OTkiLCJpbWFnZURvY2lkIjoiMTIzNTY3NDAzODU2MjUyMDI3ODkiLCJyZHMiOiJQQ18xMDQ4MTkzMTQxNTMyOTg0Mjk3N3xQUk9EX1BDXzEwNDgxOTMxNDE1MzI5ODQyOTc3IiwicXVlcnkiOiJtYXJ6aXBhbiJ9",
      "serpapi_link": "https://serpapi.com/search.json?engine=google_immersive_product&page_token=eyJlaSI6ImJDOEtaNmV3RUo2dmlMTVAwT0xELUE0IiwicHJvZHVjdGlkIjoiIiwiY2F0YWxvZ2lkIjoiOTIxMTg3MDI2NjQ2OTAzMzQ5MiIsInZjIjoiIiwidnNjIjoiIiwiaGVhZGxpbmVPZmZlckRvY2lkIjoiMTc0OTg3MjM1OTU4MDYxMjg1OTkiLCJpbWFnZURvY2lkIjoiMTIzNTY3NDAzODU2MjUyMDI3ODkiLCJyZHMiOiJQQ18xMDQ4MTkzMTQxNTMyOTg0Mjk3N3xQUk9EX1BDXzEwNDgxOTMxNDE1MzI5ODQyOTc3IiwicXVlcnkiOiJtYXJ6aXBhbiJ9"
    },
    {
      "category": "Popular products",
      "thumbnail": "https://serpapi.com/searches/670a2f6ba775f2c583499ec8/images/5196beefa97782983066e01e9f28f30f4af1646319b837a60f891545171e7ce0.jpeg",
      "source_logo": "https://serpapi.com/searches/670a2f6ba775f2c583499ec8/images/5196beefa97782983066e01e9f28f30fdbf9a34f87e34546e24c75a567b2dd3dfa98b79909abd150.png",
      "source": "The Vermont Country Store",
      "title": "The Vermont Country Store Marzipan Candy Fruit",
      "rating": 4.5,
      "reviews": 108,
      "price": "$14.95",
      "extracted_price": 14.95,
      "immersive_product_page_token": "eyJlaSI6ImJDOEtaNmV3RUo2dmlMTVAwT0xELUE0IiwicHJvZHVjdGlkIjoiIiwiY2F0YWxvZ2lkIjoiMTY2MzQ5NzY5OTk4NjcyMDY1OTgiLCJ2YyI6IiIsInZzYyI6IiIsImhlYWRsaW5lT2ZmZXJEb2NpZCI6IjEyMDk2MzEyMzU5NTU0NTA5MTU1IiwiaW1hZ2VEb2NpZCI6IjEwNjc4NDMyNjAxNzMyMjI2NTY5IiwicmRzIjoiQ0lEXzE2NjM0OTc2OTk5ODY3MjA2NTk4fFBST0RfQ0lEXzE2NjM0OTc2OTk5ODY3MjA2NTk4IiwicXVlcnkiOiJtYXJ6aXBhbiJ9",
      "serpapi_link": "https://serpapi.com/search.json?engine=google_immersive_product&page_token=eyJlaSI6ImJDOEtaNmV3RUo2dmlMTVAwT0xELUE0IiwicHJvZHVjdGlkIjoiIiwiY2F0YWxvZ2lkIjoiMTY2MzQ5NzY5OTk4NjcyMDY1OTgiLCJ2YyI6IiIsInZzYyI6IiIsImhlYWRsaW5lT2ZmZXJEb2NpZCI6IjEyMDk2MzEyMzU5NTU0NTA5MTU1IiwiaW1hZ2VEb2NpZCI6IjEwNjc4NDMyNjAxNzMyMjI2NTY5IiwicmRzIjoiQ0lEXzE2NjM0OTc2OTk5ODY3MjA2NTk4fFBST0RfQ0lEXzE2NjM0OTc2OTk5ODY3MjA2NTk4IiwicXVlcnkiOiJtYXJ6aXBhbiJ9"
    },
    {
      "category": "Popular products",
      "thumbnail": "https://serpapi.com/searches/670a2f6ba775f2c583499ec8/images/5196beefa97782983066e01e9f28f30fdf27cea685e60f48e327fdcfeda2a51e.jpeg",
      "source_logo": "https://serpapi.com/searches/670a2f6ba775f2c583499ec8/images/5196beefa97782983066e01e9f28f30f5baaa0da21db7ef26567b48835eb686de987f1c58d00ed66.png",
      "source": "ShopRite",
      "title": "Solo Marzipan 8 oz",
      "price": "$5.79",
      "extracted_price": 5.79,
      "immersive_product_page_token": "eyJlaSI6ImJDOEtaNmV3RUo2dmlMTVAwT0xELUE0IiwicHJvZHVjdGlkIjoiIiwiY2F0YWxvZ2lkIjoiNzY1ODg5Mzc1NDA0MzMyNjI4MyIsInZjIjoiIiwidnNjIjoiIiwiaGVhZGxpbmVPZmZlckRvY2lkIjoiMTA1Mzg0NTg2MTU5MTQyMzMyODUiLCJpbWFnZURvY2lkIjoiMjEwOTAzNjUwMjgyNzU0MzM3OSIsInJkcyI6IiIsInF1ZXJ5IjoibWFyemlwYW4ifQ==",
      "serpapi_link": "https://serpapi.com/search.json?engine=google_immersive_product&page_token=eyJlaSI6ImJDOEtaNmV3RUo2dmlMTVAwT0xELUE0IiwicHJvZHVjdGlkIjoiIiwiY2F0YWxvZ2lkIjoiNzY1ODg5Mzc1NDA0MzMyNjI4MyIsInZjIjoiIiwidnNjIjoiIiwiaGVhZGxpbmVPZmZlckRvY2lkIjoiMTA1Mzg0NTg2MTU5MTQyMzMyODUiLCJpbWFnZURvY2lkIjoiMjEwOTAzNjUwMjgyNzU0MzM3OSIsInJkcyI6IiIsInF1ZXJ5IjoibWFyemlwYW4ifQ%3D%3D"
    },
    {
      "category": "Popular products",
      "thumbnail": "https://serpapi.com/searches/670a2f6ba775f2c583499ec8/images/5196beefa97782983066e01e9f28f30fa72a244c8a2eb517134674293fefb653.jpeg",
      "source_logo": "https://serpapi.com/searches/670a2f6ba775f2c583499ec8/images/5196beefa97782983066e01e9f28f30fe53d3299b6d689a1273f0fe4ffbce17f670e104bc8d3d7e8.png",
      "source": "Amazon.com",
      "title": "Bergen Marzipan Assorted Fruit",
      "rating": 4.7,
      "reviews": 160,
      "price": "$10.92",
      "extracted_price": 10.92,
      "immersive_product_page_token": "eyJlaSI6ImJDOEtaNmV3RUo2dmlMTVAwT0xELUE0IiwicHJvZHVjdGlkIjoiIiwiY2F0YWxvZ2lkIjoiNjExNDE0OTMyMTk5NDY4ODkzOSIsInZjIjoiIiwidnNjIjoiIiwiaGVhZGxpbmVPZmZlckRvY2lkIjoiNTE1NTAxMTA1ODI5ODE4ODExNyIsImltYWdlRG9jaWQiOiIxMzc3MjE1NDg4MzYwNjQwMjM1IiwicmRzIjoiUENfOTk4NTcyMDEyOTExNTAzODAxMnxQUk9EX1BDXzk5ODU3MjAxMjkxMTUwMzgwMTIiLCJxdWVyeSI6Im1hcnppcGFuIn0=",
      "serpapi_link": "https://serpapi.com/search.json?engine=google_immersive_product&page_token=eyJlaSI6ImJDOEtaNmV3RUo2dmlMTVAwT0xELUE0IiwicHJvZHVjdGlkIjoiIiwiY2F0YWxvZ2lkIjoiNjExNDE0OTMyMTk5NDY4ODkzOSIsInZjIjoiIiwidnNjIjoiIiwiaGVhZGxpbmVPZmZlckRvY2lkIjoiNTE1NTAxMTA1ODI5ODE4ODExNyIsImltYWdlRG9jaWQiOiIxMzc3MjE1NDg4MzYwNjQwMjM1IiwicmRzIjoiUENfOTk4NTcyMDEyOTExNTAzODAxMnxQUk9EX1BDXzk5ODU3MjAxMjkxMTUwMzgwMTIiLCJxdWVyeSI6Im1hcnppcGFuIn0%3D"
    },
    {
      "category": "Popular products",
      "thumbnail": "https://serpapi.com/searches/670a2f6ba775f2c583499ec8/images/5196beefa97782983066e01e9f28f30fa2f9536ab69579e1e7e010d517be74b5.jpeg",
      "source_logo": "https://serpapi.com/searches/670a2f6ba775f2c583499ec8/images/5196beefa97782983066e01e9f28f30fed5f202e77783233abc6aeb4eca59d662084c1887e4ea8a5.png",
      "source": "Nuts.com",
      "title": "Nuts.com Marzipan",
      "rating": 5.0,
      "reviews": 25,
      "price": "$54.95",
      "extracted_price": 54.95,
      "original_price": "$65",
      "extracted_original_price": 65,
      "delivery": "Free $59+",
      "extensions": [
        "15% OFF"
      ],
      "immersive_product_page_token": "eyJlaSI6ImJDOEtaNmV3RUo2dmlMTVAwT0xELUE0IiwicHJvZHVjdGlkIjoiIiwiY2F0YWxvZ2lkIjoiNDU2NTg1NTc4NTczNzEwMjgyNiIsInZjIjoiIiwidnNjIjoiIiwiaGVhZGxpbmVPZmZlckRvY2lkIjoiNzE4MTg1ODQ3Njg5NTQ2ODQ0MSIsImltYWdlRG9jaWQiOiI1Njk5NzczMDM2MTk4MjMyMzUwIiwicmRzIjoiQ0lEXzQ1NjU4NTU3ODU3MzcxMDI4MjZ8UFJPRF9DSURfNDU2NTg1NTc4NTczNzEwMjgyNiIsInF1ZXJ5IjoibWFyemlwYW4ifQ==",
      "serpapi_link": "https://serpapi.com/search.json?engine=google_immersive_product&page_token=eyJlaSI6ImJDOEtaNmV3RUo2dmlMTVAwT0xELUE0IiwicHJvZHVjdGlkIjoiIiwiY2F0YWxvZ2lkIjoiNDU2NTg1NTc4NTczNzEwMjgyNiIsInZjIjoiIiwidnNjIjoiIiwiaGVhZGxpbmVPZmZlckRvY2lkIjoiNzE4MTg1ODQ3Njg5NTQ2ODQ0MSIsImltYWdlRG9jaWQiOiI1Njk5NzczMDM2MTk4MjMyMzUwIiwicmRzIjoiQ0lEXzQ1NjU4NTU3ODU3MzcxMDI4MjZ8UFJPRF9DSURfNDU2NTg1NTc4NTczNzEwMjgyNiIsInF1ZXJ5IjoibWFyemlwYW4ifQ%3D%3D"
    },
    {
      "category": "Popular products",
      "thumbnail": "https://serpapi.com/searches/670a2f6ba775f2c583499ec8/images/5196beefa97782983066e01e9f28f30f2d5dd6889752655ab4c9e93436ddf648.jpeg",
      "source_logo": "https://serpapi.com/searches/670a2f6ba775f2c583499ec8/images/5196beefa97782983066e01e9f28f30fd4943a76073ab710af95626ab77e625414c283abcbc8fe90.png",
      "source": "thetasteofgermany.com",
      "title": "Niederegger Chocolate Covered Marzipan",
      "rating": 4.6,
      "reviews": 200,
      "price": "$5.95",
      "extracted_price": 5.95,
      "immersive_product_page_token": "eyJlaSI6ImJDOEtaNmV3RUo2dmlMTVAwT0xELUE0IiwicHJvZHVjdGlkIjoiIiwiY2F0YWxvZ2lkIjoiODUwNjc5NDk1MTY4MTY3ODA4NyIsInZjIjoiIiwidnNjIjoiIiwiaGVhZGxpbmVPZmZlckRvY2lkIjoiMTM1NjYxNzg2ODA1ODExMjk3NjgiLCJpbWFnZURvY2lkIjoiOTU0OTE2Nzg0OTEwMjcyNzIyMiIsInJkcyI6IlBDXzkxOTMxMzE3NzU2NDEwMjk4ODF8UFJPRF9QQ185MTkzMTMxNzc1NjQxMDI5ODgxIiwicXVlcnkiOiJtYXJ6aXBhbiJ9",
      "serpapi_link": "https://serpapi.com/search.json?engine=google_immersive_product&page_token=eyJlaSI6ImJDOEtaNmV3RUo2dmlMTVAwT0xELUE0IiwicHJvZHVjdGlkIjoiIiwiY2F0YWxvZ2lkIjoiODUwNjc5NDk1MTY4MTY3ODA4NyIsInZjIjoiIiwidnNjIjoiIiwiaGVhZGxpbmVPZmZlckRvY2lkIjoiMTM1NjYxNzg2ODA1ODExMjk3NjgiLCJpbWFnZURvY2lkIjoiOTU0OTE2Nzg0OTEwMjcyNzIyMiIsInJkcyI6IlBDXzkxOTMxMzE3NzU2NDEwMjk4ODF8UFJPRF9QQ185MTkzMTMxNzc1NjQxMDI5ODgxIiwicXVlcnkiOiJtYXJ6aXBhbiJ9"
    },
    {
      "category": "In stores nearby",
      "thumbnail": "https://encrypted-tbn0.gstatic.com/shopping?q=tbn:ANd9GcRjpq4s0HBqr60q4BhyZ6H2t9OFD-1rPTzA-eSsfYfC7XlsR4ob_po3q-xNgQNFseOdTS5c6iQv",
      "source_logo": "https://encrypted-tbn0.gstatic.com/favicon-tbn?q=tbn%3AANd9GcTgDJw2mofi7kQOWQDu65XUMCogtBFyaL3uW1_L0YswzEotE9DR3MUFprG9U6UTG7noAIxhyS1gZPaJReHMyGVoRNkSYQ",
      "source": "H-E-B",
      "title": "Odense Marzipan Almond Candy Dough",
      "rating": 5.0,
      "reviews": 4,
      "price": "$5.17",
      "extracted_price": 5.17,
      "location": "10 mi \u00b7 In stock",
      "immersive_product_page_token": "eyJlaSI6ImJDOEtaNmV3RUo2dmlMTVAwT0xELUE0IiwicHJvZHVjdGlkIjoiIiwiY2F0YWxvZ2lkIjoiMjIzOTEwOTA3NzQ2NDU4MzUzIiwidmMiOiIiLCJ2c2MiOiIiLCJoZWFkbGluZU9mZmVyRG9jaWQiOiIxNjY0NjIxNzExNzM3MzU4NjczOSIsImltYWdlRG9jaWQiOiIxODQyOTgyMTA5NzA4MTUwMzk0OCIsInJkcyI6IlBDXzgwNzMzODk0Mzk2OTAzOTUzMTd8UFJPRF9QQ184MDczMzg5NDM5NjkwMzk1MzE3IiwicXVlcnkiOiJtYXJ6aXBhbiJ9",
      "serpapi_link": "https://serpapi.com/search.json?engine=google_immersive_product&page_token=eyJlaSI6ImJDOEtaNmV3RUo2dmlMTVAwT0xELUE0IiwicHJvZHVjdGlkIjoiIiwiY2F0YWxvZ2lkIjoiMjIzOTEwOTA3NzQ2NDU4MzUzIiwidmMiOiIiLCJ2c2MiOiIiLCJoZWFkbGluZU9mZmVyRG9jaWQiOiIxNjY0NjIxNzExNzM3MzU4NjczOSIsImltYWdlRG9jaWQiOiIxODQyOTgyMTA5NzA4MTUwMzk0OCIsInJkcyI6IlBDXzgwNzMzODk0Mzk2OTAzOTUzMTd8UFJPRF9QQ184MDczMzg5NDM5NjkwMzk1MzE3IiwicXVlcnkiOiJtYXJ6aXBhbiJ9"
    },
    {
      "category": "In stores nearby",
      "thumbnail": "https://encrypted-tbn2.gstatic.com/shopping?q=tbn:ANd9GcTi-Qq9bb1TRRzLM8ojhUwaSzCpTSytzcjm-gTba0f0ui9yPl-lAUoG3MwDTU-c6qXBPHbLco1t",
      "source_logo": "https://encrypted-tbn1.gstatic.com/favicon-tbn?q=tbn%3AANd9GcR9Yef8GkG9ifgqPlhz64BpIGI6U861lsZrZ5bwK7CjiFmXZVaAplzu0KMpK0UyBFOimNERYVE7lQZkPX-lFmWSsqZ5pjmpKvBXAZQ",
      "source": "World Market",
      "title": "Niederegger Chocolate Covered Marzipan Loaf",
      "rating": 4.6,
      "reviews": 200,
      "price": "$5.59",
      "extracted_price": 5.59,
      "original_price": "$7",
      "extracted_original_price": 7,
      "location": "13 mi \u00b7 In stock",
      "extensions": [
        "20% OFF"
      ],
      "immersive_product_page_token": "eyJlaSI6ImJDOEtaNmV3RUo2dmlMTVAwT0xELUE0IiwicHJvZHVjdGlkIjoiIiwiY2F0YWxvZ2lkIjoiMTE3Mjk0NTE3MzU0MDY5NDc2NjMiLCJ2YyI6IiIsInZzYyI6IiIsImhlYWRsaW5lT2ZmZXJEb2NpZCI6IjExMzY4MDIxMDgwNTYzMTMxNTY3IiwiaW1hZ2VEb2NpZCI6IjE1Nzc1NzcwMDA2MjcxOTMwNTE4IiwicmRzIjoiUENfOTE5MzEzMTc3NTY0MTAyOTg4MXxQUk9EX1BDXzkxOTMxMzE3NzU2NDEwMjk4ODEiLCJxdWVyeSI6Im1hcnppcGFuIn0=",
      "serpapi_link": "https://serpapi.com/search.json?engine=google_immersive_product&page_token=eyJlaSI6ImJDOEtaNmV3RUo2dmlMTVAwT0xELUE0IiwicHJvZHVjdGlkIjoiIiwiY2F0YWxvZ2lkIjoiMTE3Mjk0NTE3MzU0MDY5NDc2NjMiLCJ2YyI6IiIsInZzYyI6IiIsImhlYWRsaW5lT2ZmZXJEb2NpZCI6IjExMzY4MDIxMDgwNTYzMTMxNTY3IiwiaW1hZ2VEb2NpZCI6IjE1Nzc1NzcwMDA2MjcxOTMwNTE4IiwicmRzIjoiUENfOTE5MzEzMTc3NTY0MTAyOTg4MXxQUk9EX1BDXzkxOTMxMzE3NzU2NDEwMjk4ODEiLCJxdWVyeSI6Im1hcnppcGFuIn0%3D"
    },
    {
      "category": "In stores nearby",
      "thumbnail": "https://encrypted-tbn1.gstatic.com/shopping?q=tbn:ANd9GcSFd2LOgFrv3WT3fOtUr85mFdl_0PaJIJJ-A8cMl_iVbAxauES6vD3V5824uLQfU3W4-VWr4jE",
      "source_logo": "https://encrypted-tbn1.gstatic.com/favicon-tbn?q=tbn%3AANd9GcR9Yef8GkG9ifgqPlhz64BpIGI6U861lsZrZ5bwK7CjiFmXZVaAplzu0KMpK0UyBFOimNERYVE7lQZkPX-lFmWSsqZ5pjmpKvBXAZQ",
      "source": "World Market",
      "title": "World Market Odenwaelder Marzipan Mixed Fruit 8 Piece",
      "rating": 3.7,
      "reviews": 23,
      "price": "$8.79",
      "extracted_price": 8.79,
      "original_price": "$11",
      "extracted_original_price": 11,
      "location": "13 mi \u00b7 In stock",
      "extensions": [
        "20% OFF"
      ],
      "immersive_product_page_token": "eyJlaSI6ImJDOEtaNmV3RUo2dmlMTVAwT0xELUE0IiwicHJvZHVjdGlkIjoiIiwiY2F0YWxvZ2lkIjoiNTIwMjY4MDI2Mjk3OTM2OTIxNCIsInZjIjoiIiwidnNjIjoiIiwiaGVhZGxpbmVPZmZlckRvY2lkIjoiMTEwMDE5OTE3NjgxNTgxMzgyNzgiLCJpbWFnZURvY2lkIjoiODUyNjE3MDA0NzEwMzM1MDYyNSIsInJkcyI6IkNJRF81MjAyNjgwMjYyOTc5MzY5MjE0fFBST0RfQ0lEXzUyMDI2ODAyNjI5NzkzNjkyMTQiLCJxdWVyeSI6Im1hcnppcGFuIn0=",
      "serpapi_link": "https://serpapi.com/search.json?engine=google_immersive_product&page_token=eyJlaSI6ImJDOEtaNmV3RUo2dmlMTVAwT0xELUE0IiwicHJvZHVjdGlkIjoiIiwiY2F0YWxvZ2lkIjoiNTIwMjY4MDI2Mjk3OTM2OTIxNCIsInZjIjoiIiwidnNjIjoiIiwiaGVhZGxpbmVPZmZlckRvY2lkIjoiMTEwMDE5OTE3NjgxNTgxMzgyNzgiLCJpbWFnZURvY2lkIjoiODUyNjE3MDA0NzEwMzM1MDYyNSIsInJkcyI6IkNJRF81MjAyNjgwMjYyOTc5MzY5MjE0fFBST0RfQ0lEXzUyMDI2ODAyNjI5NzkzNjkyMTQiLCJxdWVyeSI6Im1hcnppcGFuIn0%3D"
    },
    {
      "category": "In stores nearby",
      "thumbnail": "https://encrypted-tbn2.gstatic.com/shopping?q=tbn:ANd9GcS7Vk8PORWXRJpjAIu42OWZOAFjztOW61dx0h-ypO5hBsTlGbz6OLz-zAzbDjEQ21N-n8Pt9Eo-",
      "source_logo": "https://encrypted-tbn1.gstatic.com/favicon-tbn?q=tbn%3AANd9GcR9Yef8GkG9ifgqPlhz64BpIGI6U861lsZrZ5bwK7CjiFmXZVaAplzu0KMpK0UyBFOimNERYVE7lQZkPX-lFmWSsqZ5pjmpKvBXAZQ",
      "source": "World Market",
      "title": "World Market Mirabell Mozart Marzipan Gift Box",
      "rating": 3.6,
      "reviews": 19,
      "price": "$13.59",
      "extracted_price": 13.59,
      "original_price": "$17",
      "extracted_original_price": 17,
      "location": "13 mi \u00b7 In stock",
      "extensions": [
        "20% OFF"
      ],
      "immersive_product_page_token": "eyJlaSI6ImJDOEtaNmV3RUo2dmlMTVAwT0xELUE0IiwicHJvZHVjdGlkIjoiIiwiY2F0YWxvZ2lkIjoiODM4NTQzNzMzNDY1MzcwMTcwOSIsInZjIjoiIiwidnNjIjoiIiwiaGVhZGxpbmVPZmZlckRvY2lkIjoiNDg4NDQ4OTA1MDk5OTI1NjgzMSIsImltYWdlRG9jaWQiOiIzNjMxODU1NTc0NTQ1ODYyNTU4IiwicmRzIjoiQ0lEXzgzODU0MzczMzQ2NTM3MDE3MDl8UFJPRF9DSURfODM4NTQzNzMzNDY1MzcwMTcwOSIsInF1ZXJ5IjoibWFyemlwYW4ifQ==",
      "serpapi_link": "https://serpapi.com/search.json?engine=google_immersive_product&page_token=eyJlaSI6ImJDOEtaNmV3RUo2dmlMTVAwT0xELUE0IiwicHJvZHVjdGlkIjoiIiwiY2F0YWxvZ2lkIjoiODM4NTQzNzMzNDY1MzcwMTcwOSIsInZjIjoiIiwidnNjIjoiIiwiaGVhZGxpbmVPZmZlckRvY2lkIjoiNDg4NDQ4OTA1MDk5OTI1NjgzMSIsImltYWdlRG9jaWQiOiIzNjMxODU1NTc0NTQ1ODYyNTU4IiwicmRzIjoiQ0lEXzgzODU0MzczMzQ2NTM3MDE3MDl8UFJPRF9DSURfODM4NTQzNzMzNDY1MzcwMTcwOSIsInF1ZXJ5IjoibWFyemlwYW4ifQ%3D%3D"
    },
    {
      "category": "In stores nearby",
      "thumbnail": "https://encrypted-tbn2.gstatic.com/shopping?q=tbn:ANd9GcRhEpKyN62KjlQ1uzsCxyeBD8jKuUda_QX1_iJjtv5QQ9o4PxkTt0Vbwp15cm5wjQu27Y75FYf6",
      "source_logo": "https://encrypted-tbn1.gstatic.com/favicon-tbn?q=tbn%3AANd9GcR9Yef8GkG9ifgqPlhz64BpIGI6U861lsZrZ5bwK7CjiFmXZVaAplzu0KMpK0UyBFOimNERYVE7lQZkPX-lFmWSsqZ5pjmpKvBXAZQ",
      "source": "World Market",
      "title": "Schlunder Marzipan Stollen Bites by World Market",
      "rating": 4.5,
      "reviews": 48,
      "price": "$7.99",
      "extracted_price": 7.99,
      "original_price": "$10",
      "extracted_original_price": 10,
      "location": "13 mi \u00b7 In stock",
      "extensions": [
        "20% OFF"
      ],
      "immersive_product_page_token": "eyJlaSI6ImJDOEtaNmV3RUo2dmlMTVAwT0xELUE0IiwicHJvZHVjdGlkIjoiIiwiY2F0YWxvZ2lkIjoiMjMzNTg2ODUwNDczOTIzODE5OSIsInZjIjoiIiwidnNjIjoiIiwiaGVhZGxpbmVPZmZlckRvY2lkIjoiMTQzNDQ4NjA2NDcwMDIwNzc4MTIiLCJpbWFnZURvY2lkIjoiNzQ5OTg4Mzg0NTkzMzg3MzA0NiIsInJkcyI6IkNJRF8yMzM1ODY4NTA0NzM5MjM4MTk5fFBST0RfQ0lEXzIzMzU4Njg1MDQ3MzkyMzgxOTkiLCJxdWVyeSI6Im1hcnppcGFuIn0=",
      "serpapi_link": "https://serpapi.com/search.json?engine=google_immersive_product&page_token=eyJlaSI6ImJDOEtaNmV3RUo2dmlMTVAwT0xELUE0IiwicHJvZHVjdGlkIjoiIiwiY2F0YWxvZ2lkIjoiMjMzNTg2ODUwNDczOTIzODE5OSIsInZjIjoiIiwidnNjIjoiIiwiaGVhZGxpbmVPZmZlckRvY2lkIjoiMTQzNDQ4NjA2NDcwMDIwNzc4MTIiLCJpbWFnZURvY2lkIjoiNzQ5OTg4Mzg0NTkzMzg3MzA0NiIsInJkcyI6IkNJRF8yMzM1ODY4NTA0NzM5MjM4MTk5fFBST0RfQ0lEXzIzMzU4Njg1MDQ3MzkyMzgxOTkiLCJxdWVyeSI6Im1hcnppcGFuIn0%3D"
    }
  ],
  "related_questions": [
    {
      "question": "What is marzipan called in America?",
      "snippet": "What is Marzipan? Marzipan, also known as almond candy dough, is a smooth and pliable confectionary paste made from almonds that can be used as a cake icing or molded into candies. It features a clay-like consistency that makes it easy to handle.",
      "title": "almond candy dough",
      "link": "https://www.webstaurantstore.com/blog/2920/marzipan-frangipane.html#:~:text=vs%20Almond%20Paste-,What%20is%20Marzipan%3F,makes%20it%20easy%20to%20handle.",
      "displayed_link": "https://www.webstaurantstore.com \u203a blog \u203a marzipan-fra...",
      "source_logo": "https://serpapi.com/searches/670a2f6ba775f2c583499ec8/images/aa7b737123d8bd2dd12e8ff1ccb723f661b1d2a03edb527da26a5b5f1e11e8d6.png",
      "next_page_token": "eyJvbnMiOiIxMDA0MSIsImZjIjoiRW9zQkNreEJTa2M1U210T2VubFdWMUZwVlZGb1ZUa3lPSEV6WjJOUlptZDBTR0ZXUW1ORloxVmlSRVUzVERZelUzUjRSbGhSVTFSMGNIVktRVVZrYlVWclkwZzBWRTF5U1ZWZmRFNHpha2gxRWhkaVF6aExXalpsZDBWS05uWnBURTFRTUU5TVJDMUJOQm9pUVVaWWNrVmpjVUp4WWt4aVZtYzRabmRSZFVsS1ltSm9VRGRPWlc5RlFXcFdRUSIsImZjdiI6IjMiLCJlaSI6ImJDOEtaNmV3RUo2dmlMTVAwT0xELUE0IiwicWMiOiJDZ2h0WVhKNmFYQmhiaEFBZlVQUUJqOCIsInF1ZXN0aW9uIjoiV2hhdCBpcyBtYXJ6aXBhbiBjYWxsZWQgaW4gQW1lcmljYT8iLCJsayI6IkdpSjNhR0YwSUdseklHMWhjbnBwY0dGdUlHTmhiR3hsWkNCcGJpQmhiV1Z5YVdOaCIsImJzIjoiYzUzT3NRckNNQkRHY1Z3ek9aYUFlcWhRWFF2V3NSU2NYWFdUczczWVlKcVdKRnB3OVVsY2ZBRmYwQmFSRGxVSHg0UGY5LWZZbWswMkdUcVFGbkkwRjFtaWhnU1ZvaFNraGpnbkl4T012RnNjVFBtNC1pN3hKZG1XelRvOWV5ckx3dGJPRmVEUU9nSWxqeFI1OTNNdzUzNG4tcG16RlJ1LXk0WlF0VDdIbEtBUWtmY0lneEVmVkw4UWN5eHNLcjRGbHhHa1VnZ3lwQk9DUGJtS1NMY0wxQ2tJZ19yUVhQVzMxMTJ3NUl2cW4zR185d1EiLCJpZCI6ImZjX2JDOEtaNmV3RUo2dmlMTVAwT0xELUE0XzEifQ==",
      "serpapi_link": "https://serpapi.com/search.json?device=desktop&engine=google_related_questions&google_domain=google.com&next_page_token=eyJvbnMiOiIxMDA0MSIsImZjIjoiRW9zQkNreEJTa2M1U210T2VubFdWMUZwVlZGb1ZUa3lPSEV6WjJOUlptZDBTR0ZXUW1ORloxVmlSRVUzVERZelUzUjRSbGhSVTFSMGNIVktRVVZrYlVWclkwZzBWRTF5U1ZWZmRFNHpha2gxRWhkaVF6aExXalpsZDBWS05uWnBURTFRTUU5TVJDMUJOQm9pUVVaWWNrVmpjVUp4WWt4aVZtYzRabmRSZFVsS1ltSm9VRGRPWlc5RlFXcFdRUSIsImZjdiI6IjMiLCJlaSI6ImJDOEtaNmV3RUo2dmlMTVAwT0xELUE0IiwicWMiOiJDZ2h0WVhKNmFYQmhiaEFBZlVQUUJqOCIsInF1ZXN0aW9uIjoiV2hhdCBpcyBtYXJ6aXBhbiBjYWxsZWQgaW4gQW1lcmljYT8iLCJsayI6IkdpSjNhR0YwSUdseklHMWhjbnBwY0dGdUlHTmhiR3hsWkNCcGJpQmhiV1Z5YVdOaCIsImJzIjoiYzUzT3NRckNNQkRHY1Z3ek9aYUFlcWhRWFF2V3NSU2NYWFdUczczWVlKcVdKRnB3OVVsY2ZBRmYwQmFSRGxVSHg0UGY5LWZZbWswMkdUcVFGbkkwRjFtaWhnU1ZvaFNraGpnbkl4T012RnNjVFBtNC1pN3hKZG1XelRvOWV5ckx3dGJPRmVEUU9nSWxqeFI1OTNNdzUzNG4tcG16RlJ1LXk0WlF0VDdIbEtBUWtmY0lneEVmVkw4UWN5eHNLcjRGbHhHa1VnZ3lwQk9DUGJtS1NMY0wxQ2tJZ19yUVhQVzMxMTJ3NUl2cW4zR185d1EiLCJpZCI6ImZjX2JDOEtaNmV3RUo2dmlMTVAwT0xELUE0XzEifQ%3D%3D"
    },
    {
      "question": "What is marzipan supposed to taste like?",
      "snippet": "What Does Marzipan Taste Like? Marzipan has a very sweet, nutty almond flavor. Its texture is soft, chewy and slightly rough due to the ground up almonds.",
      "title": "What Is Marzipan? | Cooking School - Food Network",
      "date": "Dec 6, 2021",
      "link": "https://www.foodnetwork.com/how-to/packages/food-network-essentials/what-is-marzipan#:~:text=What%20Does%20Marzipan%20Taste%20Like,to%20the%20ground%20up%20almonds.",
      "displayed_link": "https://www.foodnetwork.com \u203a food-network-essentials",
      "thumbnail": "https://encrypted-tbn0.gstatic.com/images?q=tbn:ANd9GcT4qtdMTTV41Me5sQJRT28ePepiJOxHwBQyhTrJI7aGrQ&s",
      "source_logo": "https://serpapi.com/searches/670a2f6ba775f2c583499ec8/images/aa7b737123d8bd2dd12e8ff1ccb723f63a803b624ffac37d3c6713f0a78c6b9a.png",
      "next_page_token": "eyJvbnMiOiIxMDA0MSIsImZjIjoiRW9zQkNreEJTa2M1U210T2VubFdWMUZwVlZGb1ZUa3lPSEV6WjJOUlptZDBTR0ZXUW1ORloxVmlSRVUzVERZelUzUjRSbGhSVTFSMGNIVktRVVZrYlVWclkwZzBWRTF5U1ZWZmRFNHpha2gxRWhkaVF6aExXalpsZDBWS05uWnBURTFRTUU5TVJDMUJOQm9pUVVaWWNrVmpjVUp4WWt4aVZtYzRabmRSZFVsS1ltSm9VRGRPWlc5RlFXcFdRUSIsImZjdiI6IjMiLCJlaSI6ImJDOEtaNmV3RUo2dmlMTVAwT0xELUE0IiwicWMiOiJDZ2h0WVhKNmFYQmhiaEFBZlVQUUJqOCIsInF1ZXN0aW9uIjoiV2hhdCBpcyBtYXJ6aXBhbiBzdXBwb3NlZCB0byB0YXN0ZSBsaWtlPyIsImxrIjoiR2lkM2FHRjBJR2x6SUcxaGNucHBjR0Z1SUhOMWNIQnZjMlZrSUhSdklIUmhjM1JsSUd4cGEyVSIsImJzIjoiYzUzT3NRckNNQkRHY1Z3ek9aYUFlcWhRWFF2V3NSU2NYWFdUczczWVlKcVdKRnB3OVVsY2ZBRmYwQmFSRGxVSHg0UGY5LWZZbWswMkdUcVFGbkkwRjFtaWhnU1ZvaFNraGpnbkl4T012RnNjVFBtNC1pN3hKZG1XelRvOWV5ckx3dGJPRmVEUU9nSWxqeFI1OTNNdzUzNG4tcG16RlJ1LXk0WlF0VDdIbEtBUWtmY0lneEVmVkw4UWN5eHNLcjRGbHhHa1VnZ3lwQk9DUGJtS1NMY0wxQ2tJZ19yUVhQVzMxMTJ3NUl2cW4zR185d1EiLCJpZCI6ImZjX2JDOEtaNmV3RUo2dmlMTVAwT0xELUE0XzEifQ==",
      "serpapi_link": "https://serpapi.com/search.json?device=desktop&engine=google_related_questions&google_domain=google.com&next_page_token=eyJvbnMiOiIxMDA0MSIsImZjIjoiRW9zQkNreEJTa2M1U210T2VubFdWMUZwVlZGb1ZUa3lPSEV6WjJOUlptZDBTR0ZXUW1ORloxVmlSRVUzVERZelUzUjRSbGhSVTFSMGNIVktRVVZrYlVWclkwZzBWRTF5U1ZWZmRFNHpha2gxRWhkaVF6aExXalpsZDBWS05uWnBURTFRTUU5TVJDMUJOQm9pUVVaWWNrVmpjVUp4WWt4aVZtYzRabmRSZFVsS1ltSm9VRGRPWlc5RlFXcFdRUSIsImZjdiI6IjMiLCJlaSI6ImJDOEtaNmV3RUo2dmlMTVAwT0xELUE0IiwicWMiOiJDZ2h0WVhKNmFYQmhiaEFBZlVQUUJqOCIsInF1ZXN0aW9uIjoiV2hhdCBpcyBtYXJ6aXBhbiBzdXBwb3NlZCB0byB0YXN0ZSBsaWtlPyIsImxrIjoiR2lkM2FHRjBJR2x6SUcxaGNucHBjR0Z1SUhOMWNIQnZjMlZrSUhSdklIUmhjM1JsSUd4cGEyVSIsImJzIjoiYzUzT3NRckNNQkRHY1Z3ek9aYUFlcWhRWFF2V3NSU2NYWFdUczczWVlKcVdKRnB3OVVsY2ZBRmYwQmFSRGxVSHg0UGY5LWZZbWswMkdUcVFGbkkwRjFtaWhnU1ZvaFNraGpnbkl4T012RnNjVFBtNC1pN3hKZG1XelRvOWV5ckx3dGJPRmVEUU9nSWxqeFI1OTNNdzUzNG4tcG16RlJ1LXk0WlF0VDdIbEtBUWtmY0lneEVmVkw4UWN5eHNLcjRGbHhHa1VnZ3lwQk9DUGJtS1NMY0wxQ2tJZ19yUVhQVzMxMTJ3NUl2cW4zR185d1EiLCJpZCI6ImZjX2JDOEtaNmV3RUo2dmlMTVAwT0xELUE0XzEifQ%3D%3D"
    },
    {
      "question": "What is real marzipan made of?",
      "snippet": "Marzipan is a confection consisting primarily of sugar and almond meal (ground almonds), sometimes augmented with almond oil or extract.",
      "title": "Marzipan - Wikipedia",
      "link": "https://en.wikipedia.org/wiki/Marzipan#:~:text=Marzipan%20is%20a%20confection%20consisting,with%20almond%20oil%20or%20extract.",
      "displayed_link": "https://en.wikipedia.org \u203a wiki \u203a Marzipan",
      "next_page_token": "eyJvbnMiOiIxMDA0MSIsImZjIjoiRW9zQkNreEJTa2M1U210T2VubFdWMUZwVlZGb1ZUa3lPSEV6WjJOUlptZDBTR0ZXUW1ORloxVmlSRVUzVERZelUzUjRSbGhSVTFSMGNIVktRVVZrYlVWclkwZzBWRTF5U1ZWZmRFNHpha2gxRWhkaVF6aExXalpsZDBWS05uWnBURTFRTUU5TVJDMUJOQm9pUVVaWWNrVmpjVUp4WWt4aVZtYzRabmRSZFVsS1ltSm9VRGRPWlc5RlFXcFdRUSIsImZjdiI6IjMiLCJlaSI6ImJDOEtaNmV3RUo2dmlMTVAwT0xELUE0IiwicWMiOiJDZ2h0WVhKNmFYQmhiaEFBZlVQUUJqOCIsInF1ZXN0aW9uIjoiV2hhdCBpcyByZWFsIG1hcnppcGFuIG1hZGUgb2Y/IiwibGsiOiJHaDEzYUdGMElHbHpJSEpsWVd3Z2JXRnllbWx3WVc0Z2JXRmtaU0J2WmciLCJicyI6ImM1M09zUXJDTUJER2NWd3pPWmFBZXFoUVhRdldzUlNjWFhXVHM3M1lZSnFXSkZwdzlVbGNmQUZmMEJhUkRsVUh4NFBmOS1mWW1rMDJHVHFRRm5JMEYxbWloZ1NWb2hTa2hqZ25JeE9NdkZzY1RQbTQtaTd4SmRtV3pUbzlleXJMd3RiT0ZlRFFPZ0lsanhSNTkzTXc1MzRuLXBtekZSdS15NFpRdFQ3SGxLQVFrZmNJZ3hFZlZMOFFjeXhzS3I0Rmx4R2tVZ2d5cEJPQ1BibUtTTGNMMUNrSWdfclFYUFczMTEydzVJdnFuM0dfOXdRIiwiaWQiOiJmY19iQzhLWjZld0VKNnZpTE1QME9MRC1BNF8xIn0=",
      "serpapi_link": "https://serpapi.com/search.json?device=desktop&engine=google_related_questions&google_domain=google.com&next_page_token=eyJvbnMiOiIxMDA0MSIsImZjIjoiRW9zQkNreEJTa2M1U210T2VubFdWMUZwVlZGb1ZUa3lPSEV6WjJOUlptZDBTR0ZXUW1ORloxVmlSRVUzVERZelUzUjRSbGhSVTFSMGNIVktRVVZrYlVWclkwZzBWRTF5U1ZWZmRFNHpha2gxRWhkaVF6aExXalpsZDBWS05uWnBURTFRTUU5TVJDMUJOQm9pUVVaWWNrVmpjVUp4WWt4aVZtYzRabmRSZFVsS1ltSm9VRGRPWlc5RlFXcFdRUSIsImZjdiI6IjMiLCJlaSI6ImJDOEtaNmV3RUo2dmlMTVAwT0xELUE0IiwicWMiOiJDZ2h0WVhKNmFYQmhiaEFBZlVQUUJqOCIsInF1ZXN0aW9uIjoiV2hhdCBpcyByZWFsIG1hcnppcGFuIG1hZGUgb2Y%2FIiwibGsiOiJHaDEzYUdGMElHbHpJSEpsWVd3Z2JXRnllbWx3WVc0Z2JXRmtaU0J2WmciLCJicyI6ImM1M09zUXJDTUJER2NWd3pPWmFBZXFoUVhRdldzUlNjWFhXVHM3M1lZSnFXSkZwdzlVbGNmQUZmMEJhUkRsVUh4NFBmOS1mWW1rMDJHVHFRRm5JMEYxbWloZ1NWb2hTa2hqZ25JeE9NdkZzY1RQbTQtaTd4SmRtV3pUbzlleXJMd3RiT0ZlRFFPZ0lsanhSNTkzTXc1MzRuLXBtekZSdS15NFpRdFQ3SGxLQVFrZmNJZ3hFZlZMOFFjeXhzS3I0Rmx4R2tVZ2d5cEJPQ1BibUtTTGNMMUNrSWdfclFYUFczMTEydzVJdnFuM0dfOXdRIiwiaWQiOiJmY19iQzhLWjZld0VKNnZpTE1QME9MRC1BNF8xIn0%3D"
    },
    {
      "question": "What's the difference between marzipan and frangipane?",
      "snippet": "Frangipane is a rich, cream-based filling, while marzipan is a thick paste mostly used for decorative purposes. The main thing they have in common is the almonds required to make each one, but beyond that, they're wildly different \u2014 especially in consistency \u2014 meaning you'll find them used differently, too.",
      "title": "What's The Main Difference Between Frangipane And Marzipan? - Yahoo",
      "date": "Dec 8, 2023",
      "link": "https://www.yahoo.com/lifestyle/whats-main-difference-between-frangipane-161737784.html#:~:text=Frangipane%20is%20a%20rich%2C%20cream,find%20them%20used%20differently%2C%20too.",
      "displayed_link": "https://www.yahoo.com \u203a lifestyle \u203a whats-main-differen...",
      "source_logo": "https://serpapi.com/searches/670a2f6ba775f2c583499ec8/images/aa7b737123d8bd2dd12e8ff1ccb723f61a8dc4dcb50fc01f365982ec682b2498.png",
      "next_page_token": "eyJvbnMiOiIxMDA0MSIsImZjIjoiRW9zQkNreEJTa2M1U210T2VubFdWMUZwVlZGb1ZUa3lPSEV6WjJOUlptZDBTR0ZXUW1ORloxVmlSRVUzVERZelUzUjRSbGhSVTFSMGNIVktRVVZrYlVWclkwZzBWRTF5U1ZWZmRFNHpha2gxRWhkaVF6aExXalpsZDBWS05uWnBURTFRTUU5TVJDMUJOQm9pUVVaWWNrVmpjVUp4WWt4aVZtYzRabmRSZFVsS1ltSm9VRGRPWlc5RlFXcFdRUSIsImZjdiI6IjMiLCJlaSI6ImJDOEtaNmV3RUo2dmlMTVAwT0xELUE0IiwicWMiOiJDZ2h0WVhKNmFYQmhiaEFBZlVQUUJqOCIsInF1ZXN0aW9uIjoiV2hhdCdzIHRoZSBkaWZmZXJlbmNlIGJldHdlZW4gbWFyemlwYW4gYW5kIGZyYW5naXBhbmU/IiwibGsiOiJjNU15TGM5SUxGRXZWaWpKU0ZWSXlVeExTeTFLelV0T1ZVaEtMU2xQVGMxVHlFMHNxc29zU014VFNNeExVVWdyU3N4TEJfRlNBUSIsImJzIjoiYzUzT3NRckNNQkRHY1Z3ek9aYUFlcWhRWFF2V3NSU2NYWFdUczczWVlKcVdKRnB3OVVsY2ZBRmYwQmFSRGxVSHg0UGY5LWZZbWswMkdUcVFGbkkwRjFtaWhnU1ZvaFNraGpnbkl4T012RnNjVFBtNC1pN3hKZG1XelRvOWV5ckx3dGJPRmVEUU9nSWxqeFI1OTNNdzUzNG4tcG16RlJ1LXk0WlF0VDdIbEtBUWtmY0lneEVmVkw4UWN5eHNLcjRGbHhHa1VnZ3lwQk9DUGJtS1NMY0wxQ2tJZ19yUVhQVzMxMTJ3NUl2cW4zR185d1EiLCJpZCI6ImZjX2JDOEtaNmV3RUo2dmlMTVAwT0xELUE0XzEifQ==",
      "serpapi_link": "https://serpapi.com/search.json?device=desktop&engine=google_related_questions&google_domain=google.com&next_page_token=eyJvbnMiOiIxMDA0MSIsImZjIjoiRW9zQkNreEJTa2M1U210T2VubFdWMUZwVlZGb1ZUa3lPSEV6WjJOUlptZDBTR0ZXUW1ORloxVmlSRVUzVERZelUzUjRSbGhSVTFSMGNIVktRVVZrYlVWclkwZzBWRTF5U1ZWZmRFNHpha2gxRWhkaVF6aExXalpsZDBWS05uWnBURTFRTUU5TVJDMUJOQm9pUVVaWWNrVmpjVUp4WWt4aVZtYzRabmRSZFVsS1ltSm9VRGRPWlc5RlFXcFdRUSIsImZjdiI6IjMiLCJlaSI6ImJDOEtaNmV3RUo2dmlMTVAwT0xELUE0IiwicWMiOiJDZ2h0WVhKNmFYQmhiaEFBZlVQUUJqOCIsInF1ZXN0aW9uIjoiV2hhdCdzIHRoZSBkaWZmZXJlbmNlIGJldHdlZW4gbWFyemlwYW4gYW5kIGZyYW5naXBhbmU%2FIiwibGsiOiJjNU15TGM5SUxGRXZWaWpKU0ZWSXlVeExTeTFLelV0T1ZVaEtMU2xQVGMxVHlFMHNxc29zU014VFNNeExVVWdyU3N4TEJfRlNBUSIsImJzIjoiYzUzT3NRckNNQkRHY1Z3ek9aYUFlcWhRWFF2V3NSU2NYWFdUczczWVlKcVdKRnB3OVVsY2ZBRmYwQmFSRGxVSHg0UGY5LWZZbWswMkdUcVFGbkkwRjFtaWhnU1ZvaFNraGpnbkl4T012RnNjVFBtNC1pN3hKZG1XelRvOWV5ckx3dGJPRmVEUU9nSWxqeFI1OTNNdzUzNG4tcG16RlJ1LXk0WlF0VDdIbEtBUWtmY0lneEVmVkw4UWN5eHNLcjRGbHhHa1VnZ3lwQk9DUGJtS1NMY0wxQ2tJZ19yUVhQVzMxMTJ3NUl2cW4zR185d1EiLCJpZCI6ImZjX2JDOEtaNmV3RUo2dmlMTVAwT0xELUE0XzEifQ%3D%3D"
    }
  ],
  "organic_results": [
    {
      "position": 1,
      "title": "Best Marzipan Recipe (Almond Paste)",
      "link": "https://elavegan.com/homemade-marzipan-recipe/",
      "redirect_link": "https://www.google.com/url?sa=t&source=web&rct=j&opi=89978449&url=https://elavegan.com/homemade-marzipan-recipe/&ved=2ahUKEwinlvfQsoiJAxWeF2IAHVDxEO8QFnoECFkQAQ&usg=AOvVaw2op6Cz5pd2Qf2XkllUijgo",
      "displayed_link": "https://elavegan.com \u203a Vegan Desserts",
      "thumbnail": "https://serpapi.com/searches/670a2f6ba775f2c583499ec8/images/74e90299aea3702f837f64f57da1168ca7c2ed1d62f63ebda0f6860bf9292c94.jpeg",
      "favicon": "https://serpapi.com/searches/670a2f6ba775f2c583499ec8/images/74e90299aea3702f837f64f57da1168cdf5fde6fee83453b1f20d50e253de5fe.png",
      "date": "Aug 14, 2022",
      "snippet": "This quick and easy homemade marzipan recipe contains 3 ingredients. The recipe is vegan (no raw eggs), refined sugar-free & keto-friendly!",
      "snippet_highlighted_words": [
        "marzipan"
      ],
      "rich_snippet": {
        "bottom": {
          "detected_extensions": {
            "unknown": 5.0,
            "min": 5
          },
          "extensions": [
            "5.0(91)",
            "5 min"
          ]
        }
      },
      "source": "Elavegan"
    },
    {
      "position": 2,
      "title": "Marzipan",
      "link": "https://en.wikipedia.org/wiki/Marzipan",
      "redirect_link": "https://www.google.com/url?sa=t&source=web&rct=j&opi=89978449&url=https://en.wikipedia.org/wiki/Marzipan&ved=2ahUKEwinlvfQsoiJAxWeF2IAHVDxEO8QFnoECFQQAQ&usg=AOvVaw0nD_0-W3BOWCx3jewXMQrl",
      "displayed_link": "https://en.wikipedia.org \u203a wiki \u203a Marzipan",
      "thumbnail": "https://encrypted-tbn0.gstatic.com/images?q=tbn:ANd9GcRxNA92W9MI16n1bCa-TLvdjO2mJ3BKNnQOAHB2cnl1cwrPjQvJ6xnF&usqp=CAE&s",
      "favicon": "https://serpapi.com/searches/670a2f6ba775f2c583499ec8/images/74e90299aea3702f837f64f57da1168c3afa7ef7bdb2679c8bbc356e3ae53930.png",
      "snippet": "Marzipan is a confection consisting primarily of sugar and almond meal (ground almonds), sometimes augmented with almond oil or extract.",
      "snippet_highlighted_words": [
        "Marzipan"
      ],
      "sitelinks": {
        "inline": [
          {
            "title": "L\u00fcbeck Marzipan",
            "link": "https://en.wikipedia.org/wiki/L%C3%BCbeck_Marzipan"
          },
          {
            "title": "Marzipan pig",
            "link": "https://en.wikipedia.org/wiki/Marzipan_pig"
          },
          {
            "title": "Almond meal",
            "link": "https://en.wikipedia.org/wiki/Almond_meal"
          },
          {
            "title": "Persipan",
            "link": "https://en.wikipedia.org/wiki/Persipan"
          }
        ]
      },
      "source": "Wikipedia"
    },
    {
      "position": 3,
      "title": "Homemade Marzipan (Almond Paste)",
      "link": "https://www.daringgourmet.com/how-to-make-marzipan-almond-paste/",
      "redirect_link": "https://www.google.com/url?sa=t&source=web&rct=j&opi=89978449&url=https://www.daringgourmet.com/how-to-make-marzipan-almond-paste/&ved=2ahUKEwinlvfQsoiJAxWeF2IAHVDxEO8QFnoECF0QAQ&usg=AOvVaw3XQ2UMZbAg1I3dz7H-X0AL",
      "displayed_link": "https://www.daringgourmet.com \u203a Dessert",
      "thumbnail": "https://encrypted-tbn0.gstatic.com/images?q=tbn:ANd9GcQyQtg4wJbZUwxZLH1x0q0G3--uXPlkMbxpKQVI-IaYrXDWMvvm1l9f&usqp=CAE&s",
      "favicon": "https://serpapi.com/searches/670a2f6ba775f2c583499ec8/images/74e90299aea3702f837f64f57da1168c4fd86c5b00c42e8a8a350d653cf7c9fe.png",
      "date": "Nov 4, 2023",
      "snippet": "Marzipan is a sweet confectionery paste made from ground almonds and sugar. Its flavor is commonly enhanced with almond and rose extracts. It ...",
      "snippet_highlighted_words": [
        "Marzipan"
      ],
      "rich_snippet": {
        "bottom": {
          "detected_extensions": {
            "unknown": 4.9,
            "min": 5
          },
          "extensions": [
            "4.9(430)",
            "5 min"
          ]
        }
      },
      "source": "The Daring Gourmet"
    },
    {
      "position": 4,
      "title": "Australian here. never tried marzipan. what does it even ...",
      "link": "https://www.reddit.com/r/FondantHate/comments/15fb450/australian_here_never_tried_marzipan_what_does_it/",
      "redirect_link": "https://www.google.com/url?sa=t&source=web&rct=j&opi=89978449&url=https://www.reddit.com/r/FondantHate/comments/15fb450/australian_here_never_tried_marzipan_what_does_it/&ved=2ahUKEwinlvfQsoiJAxWeF2IAHVDxEO8QFnoFCIYBEAE&usg=AOvVaw38YZFWqqdX3g848i61zV9J",
      "displayed_link": "70+ comments \u00b7 1 year ago",
      "favicon": "https://serpapi.com/searches/670a2f6ba775f2c583499ec8/images/74e90299aea3702f837f64f57da1168c20e36a7e533f76a2370b1d48da2f8721.png",
      "snippet": "Very almond-heavy flavor, and very sweet, with kind of a marshmallow-like texture. I think it tastes okay, although it's not my favorite candy.",
      "source": "Reddit \u00b7 r/FondantHate"
    },
    {
      "position": 5,
      "title": "Easy Marzipan Recipe",
      "link": "https://www.allrecipes.com/recipe/7740/marzipan/",
      "redirect_link": "https://www.google.com/url?sa=t&source=web&rct=j&opi=89978449&url=https://www.allrecipes.com/recipe/7740/marzipan/&ved=2ahUKEwinlvfQsoiJAxWeF2IAHVDxEO8QFnoECFUQAQ&usg=AOvVaw0EwsfCSHnoY_n4Dtd-M_l7",
      "displayed_link": "https://www.allrecipes.com \u203a ... \u203a Candy Recipes",
      "thumbnail": "https://encrypted-tbn0.gstatic.com/images?q=tbn:ANd9GcRw79WcmOOTMWxH9SsrGhgY-augqCPoAJRl8K1rpm60jdXVUCZ_BaMV&usqp=CAE&s",
      "favicon": "https://serpapi.com/searches/670a2f6ba775f2c583499ec8/images/74e90299aea3702f837f64f57da1168c80cc004efccde97a95116c34384bda36.png",
      "date": "Nov 23, 2023",
      "snippet": "Ingredients \u00b7 2 cups confectioners' sugar \u00b7 \u00bd pound finely ground blanched almonds \u00b7 2 egg whites \u00b7 \u00bd teaspoon salt \u00b7 \u00bd teaspoon almond extract.",
      "rich_snippet": {
        "bottom": {
          "detected_extensions": {
            "unknown": 4.5,
            "hr_min": 24
          },
          "extensions": [
            "4.5(15)",
            "24 hr 30 min"
          ]
        }
      },
      "source": "Allrecipes"
    },
    {
      "position": 6,
      "title": "Marzipan",
      "link": "https://marzipanbakery.com/",
      "redirect_link": "https://www.google.com/url?sa=t&source=web&rct=j&opi=89978449&url=https://marzipanbakery.com/&ved=2ahUKEwinlvfQsoiJAxWeF2IAHVDxEO8QFnoECFYQAQ&usg=AOvVaw3SQ1oilBRt6dGXae-idUku",
      "displayed_link": "https://marzipanbakery.com",
      "thumbnail": "https://encrypted-tbn0.gstatic.com/images?q=tbn:ANd9GcQsgkoC5yiWKb3MgjcEX5sBLU2buTbtxEO2Y-KE3t3jmc7SWOzUlnJQ&usqp=CAE&s",
      "favicon": "https://serpapi.com/searches/670a2f6ba775f2c583499ec8/images/74e90299aea3702f837f64f57da1168ca5b1c0ed4a056de3b1f089a79135f395.png",
      "snippet": "Freshly baked by the famous Marzipan Bakery in Jerusalem. 40 years ago, Mr. Ozarko, the founder of Marzipan Bakery began a quest to perfect his favorite food.",
      "snippet_highlighted_words": [
        "Marzipan",
        "Marzipan"
      ],
      "source": "marzipanbakery.com"
    },
    {
      "position": 7,
      "title": "How to Make Marzipan in 5 Minuets",
      "link": "https://m.youtube.com/watch?v=RICve3SEt2Y",
      "displayed_link": "11.2K+ views \u00b7 10 months ago",
      "thumbnail": "https://i.ytimg.com/vi/RICve3SEt2Y/mqdefault.jpg?sqp=-oaymwEFCJQBEFM&rs=AMzJL3kxtG_LdY1p1HMt7LsxOnoP0OnkSA",
      "favicon": "https://serpapi.com/searches/670a2f6ba775f2c583499ec8/images/74e90299aea3702f837f64f57da1168cd6f4eadc4655347d51f08bb038b591fe.png",
      "snippet": "Today, I will show you how to make marzipan in 5 minuets - if you can't buy it in the store, it is really simple.",
      "duration": "4:41",
      "source": "YouTube \u00b7 Backyard Chef"
    },
    {
      "position": 8,
      "title": "Best Homemade Marzipan Recipe",
      "link": "https://www.simplyrecipes.com/marzipan-recipe-5295688",
      "redirect_link": "https://www.google.com/url?sa=t&source=web&rct=j&opi=89978449&url=https://www.simplyrecipes.com/marzipan-recipe-5295688&ved=2ahUKEwinlvfQsoiJAxWeF2IAHVDxEO8QFnoECF4QAQ&usg=AOvVaw3fOh2bOwttVqvPf1QSy2Bt",
      "displayed_link": "https://www.simplyrecipes.com \u203a Recipes \u203a Desserts",
      "thumbnail": "https://encrypted-tbn0.gstatic.com/images?q=tbn:ANd9GcRf453g-PXjtBU6CMIBrKlVn8HoX_qA1Lsax7iTAeZCGae76WL3CoUr&usqp=CAE&s",
      "favicon": "https://serpapi.com/searches/670a2f6ba775f2c583499ec8/images/74e90299aea3702f837f64f57da1168c6b8d8ce9e65db07dfbdda3d59d598467.png",
      "snippet": "Marzipan is a soft, sweet, paste made with almonds and sugar. It can be eaten on its own, usually shaped into small fruits or cute animals, ...",
      "snippet_highlighted_words": [
        "Marzipan"
      ],
      "sitelinks": {
        "inline": [
          {
            "title": "Marzipan, A Dessert...",
            "link": "https://www.simplyrecipes.com/marzipan-recipe-5295688#:~:text=Marzipan%2C%20A%20Dessert%20Centuries%20Old"
          },
          {
            "title": "The Difference Between...",
            "link": "https://www.simplyrecipes.com/marzipan-recipe-5295688#:~:text=The%20Difference%20Between%20Marzipan%2C%20Almond%20Paste%2C%20and%20Frangipane"
          },
          {
            "title": "Simple Tip!",
            "link": "https://www.simplyrecipes.com/marzipan-recipe-5295688#:~:text=Simple%20Tip%21"
          }
        ]
      },
      "rich_snippet": {
        "bottom": {
          "detected_extensions": {
            "unknown": 5.0,
            "min": 5
          },
          "extensions": [
            "5.0(2)",
            "5 min"
          ]
        }
      },
      "source": "Simply Recipes"
    }
  ],
  "top_stories_link": "https://www.google.com/search?q=marzipan&sca_esv=8568a6baa21243e5&hl=en&gl=us&udm=18&sa=X&ved=2ahUKEwinlvfQsoiJAxWeF2IAHVDxEO8Q8poLegQIUxAF",
  "top_stories_serpapi_link": "https://serpapi.com/search.json?device=desktop&engine=google&gl=us&google_domain=google.com&hl=en&location=Austin%2CTexas%2CUnited+States&q=marzipan",
  "related_searches": [
    {
      "block_position": 1,
      "query": "Marzipan recipe",
      "link": "https://www.google.com/search?sca_esv=8568a6baa21243e5&hl=en&gl=us&q=Marzipan+recipe&sa=X&ved=2ahUKEwinlvfQsoiJAxWeF2IAHVDxEO8Q1QJ6BQiFARAB",
      "serpapi_link": "https://serpapi.com/search.json?device=desktop&engine=google&gl=us&google_domain=google.com&hl=en&location=Austin%2CTexas%2CUnited+States&q=Marzipan+recipe"
    },
    {
      "block_position": 1,
      "query": "Marzipan chocolate",
      "link": "https://www.google.com/search?sca_esv=8568a6baa21243e5&hl=en&gl=us&q=Marzipan+chocolate&sa=X&ved=2ahUKEwinlvfQsoiJAxWeF2IAHVDxEO8Q1QJ6BAh_EAE",
      "serpapi_link": "https://serpapi.com/search.json?device=desktop&engine=google&gl=us&google_domain=google.com&hl=en&location=Austin%2CTexas%2CUnited+States&q=Marzipan+chocolate"
    },
    {
      "block_position": 1,
      "query": "Marzipan cake",
      "link": "https://www.google.com/search?sca_esv=8568a6baa21243e5&hl=en&gl=us&q=Marzipan+cake&sa=X&ved=2ahUKEwinlvfQsoiJAxWeF2IAHVDxEO8Q1QJ6BQiBARAB",
      "serpapi_link": "https://serpapi.com/search.json?device=desktop&engine=google&gl=us&google_domain=google.com&hl=en&location=Austin%2CTexas%2CUnited+States&q=Marzipan+cake"
    },
    {
      "block_position": 1,
      "query": "Traditional marzipan recipe",
      "link": "https://www.google.com/search?sca_esv=8568a6baa21243e5&hl=en&gl=us&q=Traditional+marzipan+recipe&sa=X&ved=2ahUKEwinlvfQsoiJAxWeF2IAHVDxEO8Q1QJ6BQiCARAB",
      "serpapi_link": "https://serpapi.com/search.json?device=desktop&engine=google&gl=us&google_domain=google.com&hl=en&location=Austin%2CTexas%2CUnited+States&q=Traditional+marzipan+recipe"
    },
    {
      "block_position": 1,
      "query": "What is marzipan used for",
      "link": "https://www.google.com/search?sca_esv=8568a6baa21243e5&hl=en&gl=us&q=What+is+marzipan+used+for&sa=X&ved=2ahUKEwinlvfQsoiJAxWeF2IAHVDxEO8Q1QJ6BQiAARAB",
      "serpapi_link": "https://serpapi.com/search.json?device=desktop&engine=google&gl=us&google_domain=google.com&hl=en&location=Austin%2CTexas%2CUnited+States&q=What+is+marzipan+used+for"
    },
    {
      "block_position": 1,
      "query": "Marzipan taste",
      "link": "https://www.google.com/search?sca_esv=8568a6baa21243e5&hl=en&gl=us&q=Marzipan+taste&sa=X&ved=2ahUKEwinlvfQsoiJAxWeF2IAHVDxEO8Q1QJ6BQiEARAB",
      "serpapi_link": "https://serpapi.com/search.json?device=desktop&engine=google&gl=us&google_domain=google.com&hl=en&location=Austin%2CTexas%2CUnited+States&q=Marzipan+taste"
    },
    {
      "block_position": 1,
      "query": "Marzipan ingredients",
      "link": "https://www.google.com/search?sca_esv=8568a6baa21243e5&hl=en&gl=us&q=Marzipan+ingredients&sa=X&ved=2ahUKEwinlvfQsoiJAxWeF2IAHVDxEO8Q1QJ6BQiDARAB",
      "serpapi_link": "https://serpapi.com/search.json?device=desktop&engine=google&gl=us&google_domain=google.com&hl=en&location=Austin%2CTexas%2CUnited+States&q=Marzipan+ingredients"
    },
    {
      "block_position": 1,
      "query": "All recipes marzipan",
      "link": "https://www.google.com/search?sca_esv=8568a6baa21243e5&hl=en&gl=us&q=All+recipes+marzipan&sa=X&ved=2ahUKEwinlvfQsoiJAxWeF2IAHVDxEO8Q1QJ6BAh9EAE",
      "serpapi_link": "https://serpapi.com/search.json?device=desktop&engine=google&gl=us&google_domain=google.com&hl=en&location=Austin%2CTexas%2CUnited+States&q=All+recipes+marzipan"
    }
  ],
  "refine_this_search": [
    {
      "query": "Recipe",
      "link": "https://www.google.com/search?hl=en&gl=us&q=recipe+marzipan&shoprs=GBIqCG1hcnppcGFuMgoIEhIGUmVjaXBlYAE&sa=X&ved=2ahUKEwinlvfQsoiJAxWeF2IAHVDxEO8Qip4GKAF6BAgUECU",
      "serpapi_link": "https://serpapi.com/search.json?device=desktop&engine=google&gl=us&google_domain=google.com&hl=en&location=Austin%2CTexas%2CUnited+States&q=recipe+marzipan"
    },
    {
      "query": "Nearby",
      "link": "https://www.google.com/search?hl=en&gl=us&q=marzipan+nearby&shoprs=GAMqCG1hcnppcGFuMgwIAxIGTmVhcmJ5GAJYy4shYAE&sa=X&ved=2ahUKEwinlvfQsoiJAxWeF2IAHVDxEO8Qip4GKAJ6BAgUECY",
      "serpapi_link": "https://serpapi.com/search.json?device=desktop&engine=google&gl=us&google_domain=google.com&hl=en&location=Austin%2CTexas%2CUnited+States&q=marzipan+nearby"
    },
    {
      "query": "Get it fast",
      "link": "https://www.google.com/search?hl=en&gl=us&q=marzipan&shoprs=Eg2aAQoKCBADOAFAAkgBGBQqCG1hcnppcGFuMiQIFBILR2V0IGl0IGZhc3QiDZoBCgoIEAM4AUACSAEqBBABGAFgAQ&sa=X&ved=2ahUKEwinlvfQsoiJAxWeF2IAHVDxEO8Qip4GKAN6BAgUECc",
      "serpapi_link": "https://serpapi.com/search.json?device=desktop&engine=google&gl=us&google_domain=google.com&hl=en&location=Austin%2CTexas%2CUnited+States&q=marzipan"
    },
    {
      "query": "Buy",
      "link": "https://www.google.com/search?hl=en&gl=us&q=buy+marzipan&shoprs=GBIqCG1hcnppcGFuMgcIEhIDQnV5YAE&sa=X&ved=2ahUKEwinlvfQsoiJAxWeF2IAHVDxEO8Qip4GKAR6BAgUECg",
      "serpapi_link": "https://serpapi.com/search.json?device=desktop&engine=google&gl=us&google_domain=google.com&hl=en&location=Austin%2CTexas%2CUnited+States&q=buy+marzipan"
    },
    {
      "query": "Chocolate",
      "link": "https://www.google.com/search?hl=en&gl=us&q=chocolate+marzipan&shoprs=GAkqCG1hcnppcGFuMg0ICRIJQ2hvY29sYXRlYAE&sa=X&ved=2ahUKEwinlvfQsoiJAxWeF2IAHVDxEO8Qip4GKAV6BAgUECk",
      "serpapi_link": "https://serpapi.com/search.json?device=desktop&engine=google&gl=us&google_domain=google.com&hl=en&location=Austin%2CTexas%2CUnited+States&q=chocolate+marzipan"
    },
    {
      "query": "For Sale",
      "link": "https://www.google.com/search?hl=en&gl=us&q=marzipan+for+sale&shoprs=GBIqCG1hcnppcGFuMgwIEhIIRm9yIFNhbGVgAQ&sa=X&ved=2ahUKEwinlvfQsoiJAxWeF2IAHVDxEO8Qip4GKAZ6BAgUECo",
      "serpapi_link": "https://serpapi.com/search.json?device=desktop&engine=google&gl=us&google_domain=google.com&hl=en&location=Austin%2CTexas%2CUnited+States&q=marzipan+for+sale"
    },
    {
      "query": "Store",
      "link": "https://www.google.com/search?hl=en&gl=us&q=store+marzipan&shoprs=GBIqCG1hcnppcGFuMgkIEhIFU3RvcmVgAQ&sa=X&ved=2ahUKEwinlvfQsoiJAxWeF2IAHVDxEO8Qip4GKAd6BAgUECs",
      "serpapi_link": "https://serpapi.com/search.json?device=desktop&engine=google&gl=us&google_domain=google.com&hl=en&location=Austin%2CTexas%2CUnited+States&q=store+marzipan"
    },
    {
      "query": "On sale",
      "link": "https://www.google.com/search?hl=en&gl=us&q=marzipan+sale&shoprs=EgRKAhgBGAYqCG1hcnppcGFuMhMIBhIHT24gc2FsZRgCIgRKAhgBWMuLIWAB&sa=X&ved=2ahUKEwinlvfQsoiJAxWeF2IAHVDxEO8Qip4GKAh6BAgUECw",
      "serpapi_link": "https://serpapi.com/search.json?device=desktop&engine=google&gl=us&google_domain=google.com&hl=en&location=Austin%2CTexas%2CUnited+States&q=marzipan+sale"
    },
    {
      "query": "Price",
      "link": "https://www.google.com/search?hl=en&gl=us&q=price+marzipan&shoprs=GBIqCG1hcnppcGFuMgkIEhIFUHJpY2VgAQ&sa=X&ved=2ahUKEwinlvfQsoiJAxWeF2IAHVDxEO8Qip4GKAl6BAgUEC0",
      "serpapi_link": "https://serpapi.com/search.json?device=desktop&engine=google&gl=us&google_domain=google.com&hl=en&location=Austin%2CTexas%2CUnited+States&q=price+marzipan"
    },
    {
      "query": "Brand",
      "link": "https://www.google.com/search?hl=en&gl=us&q=brand+marzipan&shoprs=GBIqCG1hcnppcGFuMgkIEhIFQnJhbmRgAQ&sa=X&ved=2ahUKEwinlvfQsoiJAxWeF2IAHVDxEO8Qip4GKAp6BAgUEC4",
      "serpapi_link": "https://serpapi.com/search.json?device=desktop&engine=google&gl=us&google_domain=google.com&hl=en&location=Austin%2CTexas%2CUnited+States&q=brand+marzipan"
    },
    {
      "query": "Online",
      "link": "https://www.google.com/search?hl=en&gl=us&q=online+marzipan&shoprs=GBIqCG1hcnppcGFuMgoIEhIGT25saW5lYAE&sa=X&ved=2ahUKEwinlvfQsoiJAxWeF2IAHVDxEO8Qip4GKAt6BAgUEC8",
      "serpapi_link": "https://serpapi.com/search.json?device=desktop&engine=google&gl=us&google_domain=google.com&hl=en&location=Austin%2CTexas%2CUnited+States&q=online+marzipan"
    },
    {
      "query": "Walmart",
      "link": "https://www.google.com/search?hl=en&gl=us&q=walmart+marzipan&shoprs=GAIqCG1hcnppcGFuMgsIAhIHV2FsbWFydFjLiyFgAQ&sa=X&ved=2ahUKEwinlvfQsoiJAxWeF2IAHVDxEO8Qip4GKAx6BAgUEDA",
      "serpapi_link": "https://serpapi.com/search.json?device=desktop&engine=google&gl=us&google_domain=google.com&hl=en&location=Austin%2CTexas%2CUnited+States&q=walmart+marzipan",
      "thumbnail": "https://serpapi.com/searches/670a2f6ba775f2c583499ec8/images/bce36e4e2b095ce846e576186c3998d859539b6477a73f78c7c5295652e4995d.png"
    },
    {
      "query": "Images",
      "link": "https://www.google.com/search?hl=en&gl=us&q=images+marzipan&shoprs=GBIqCG1hcnppcGFuMgoIEhIGSW1hZ2VzYAE&sa=X&ved=2ahUKEwinlvfQsoiJAxWeF2IAHVDxEO8Qip4GKA16BAgUEDI",
      "serpapi_link": "https://serpapi.com/search.json?device=desktop&engine=google&gl=us&google_domain=google.com&hl=en&location=Austin%2CTexas%2CUnited+States&q=images+marzipan"
    },
    {
      "query": "Almond",
      "link": "https://www.google.com/search?hl=en&gl=us&q=almond+marzipan&shoprs=GAEqCG1hcnppcGFuMhgIARIGQWxtb25kOgwI-Of_ARD_5_8BMABYy4shYAE&sa=X&ved=2ahUKEwinlvfQsoiJAxWeF2IAHVDxEO8Qip4GKA56BAgUEDM",
      "serpapi_link": "https://serpapi.com/search.json?device=desktop&engine=google&gl=us&google_domain=google.com&hl=en&location=Austin%2CTexas%2CUnited+States&q=almond+marzipan"
    },
    {
      "query": "Bar",
      "link": "https://www.google.com/search?hl=en&gl=us&q=bar+marzipan&shoprs=GAEqCG1hcnppcGFuMhMIARIDQmFyOgoI7bc8EMSgXDAAWMuLIWAB&sa=X&ved=2ahUKEwinlvfQsoiJAxWeF2IAHVDxEO8Qip4GKA96BAgUEDQ",
      "serpapi_link": "https://serpapi.com/search.json?device=desktop&engine=google&gl=us&google_domain=google.com&hl=en&location=Austin%2CTexas%2CUnited+States&q=bar+marzipan"
    },
    {
      "query": "Ritter Sport",
      "link": "https://www.google.com/search?hl=en&gl=us&q=ritter+sport+marzipan&shoprs=GAEqCG1hcnppcGFuMhwIARIMUml0dGVyIFNwb3J0OgoIg_M8EObtSDABWMuLIWAB&sa=X&ved=2ahUKEwinlvfQsoiJAxWeF2IAHVDxEO8Qip4GKBB6BAgUEDU",
      "serpapi_link": "https://serpapi.com/search.json?device=desktop&engine=google&gl=us&google_domain=google.com&hl=en&location=Austin%2CTexas%2CUnited+States&q=ritter+sport+marzipan"
    },
    {
      "query": "Amazon",
      "link": "https://www.google.com/search?hl=en&gl=us&q=amazon+marzipan&shoprs=GAIqCG1hcnppcGFuMgoIAhIGQW1hem9uWMuLIWAB&sa=X&ved=2ahUKEwinlvfQsoiJAxWeF2IAHVDxEO8Qip4GKBF6BAgUEDY",
      "serpapi_link": "https://serpapi.com/search.json?device=desktop&engine=google&gl=us&google_domain=google.com&hl=en&location=Austin%2CTexas%2CUnited+States&q=amazon+marzipan",
      "thumbnail": "https://encrypted-tbn1.gstatic.com/faviconV2?url=https://amazon.com&client=SHOPPING&size=32&type=FAVICON&fallback_opts=TYPE,SIZE,URL&nfrp=2"
    },
    {
      "query": "Small business",
      "link": "https://www.google.com/search?hl=en&gl=us&q=marzipan&shoprs=EgJqABgWKghtYXJ6aXBhbjIcCBYSDlNtYWxsIGJ1c2luZXNzIgJqACoEEAEYAWAB&sa=X&ved=2ahUKEwinlvfQsoiJAxWeF2IAHVDxEO8Qip4GKBJ6BAgUEDg",
      "serpapi_link": "https://serpapi.com/search.json?device=desktop&engine=google&gl=us&google_domain=google.com&hl=en&location=Austin%2CTexas%2CUnited+States&q=marzipan"
    },
    {
      "query": "Free shipping",
      "link": "https://www.google.com/search?hl=en&gl=us&q=marzipan+free+shipping&shoprs=EgRSAhABGBkqCG1hcnppcGFuMhcIGRINRnJlZSBzaGlwcGluZyIEUgIQAWAB&sa=X&ved=2ahUKEwinlvfQsoiJAxWeF2IAHVDxEO8Qip4GKBN6BAgUEDk",
      "serpapi_link": "https://serpapi.com/search.json?device=desktop&engine=google&gl=us&google_domain=google.com&hl=en&location=Austin%2CTexas%2CUnited+States&q=marzipan+free+shipping"
    },
    {
      "query": "Under $20",
      "link": "https://www.google.com/search?hl=en&gl=us&q=marzipan+under+$20&shoprs=Eg0SCxEAAAAA0BJzQRgBGAUqCG1hcnppcGFuMiIIBRIJVW5kZXIgJDIwGAIiDRILEQAAAADQEnNBGAEqAhgBWMuLIWAB&sa=X&ved=2ahUKEwinlvfQsoiJAxWeF2IAHVDxEO8Qip4GKBR6BAgUEDo",
      "serpapi_link": "https://serpapi.com/search.json?device=desktop&engine=google&gl=us&google_domain=google.com&hl=en&location=Austin%2CTexas%2CUnited+States&q=marzipan+under+%2420"
    },
    {
      "query": "Target",
      "link": "https://www.google.com/search?hl=en&gl=us&q=target+marzipan&shoprs=GAIqCG1hcnppcGFuMgoIAhIGVGFyZ2V0WMuLIWAB&sa=X&ved=2ahUKEwinlvfQsoiJAxWeF2IAHVDxEO8Qip4GKBV6BAgUEDs",
      "serpapi_link": "https://serpapi.com/search.json?device=desktop&engine=google&gl=us&google_domain=google.com&hl=en&location=Austin%2CTexas%2CUnited+States&q=target+marzipan",
      "thumbnail": "https://encrypted-tbn3.gstatic.com/faviconV2?url=http://www.target.com&client=SHOPPING&size=32&type=FAVICON&fallback_opts=TYPE,SIZE,URL&nfrp=2"
    },
    {
      "query": "Amazon.com",
      "link": "https://www.google.com/search?hl=en&gl=us&q=amazon.com+marzipan&shoprs=GAIqCG1hcnppcGFuMg4IAhIKQW1hem9uLmNvbVjLiyFgAQ&sa=X&ved=2ahUKEwinlvfQsoiJAxWeF2IAHVDxEO8Qip4GKBZ6BAgUED0",
      "serpapi_link": "https://serpapi.com/search.json?device=desktop&engine=google&gl=us&google_domain=google.com&hl=en&location=Austin%2CTexas%2CUnited+States&q=amazon.com+marzipan",
      "thumbnail": "https://encrypted-tbn2.gstatic.com/faviconV2?url=http://www.amazon.com&client=SHOPPING&size=32&type=FAVICON&fallback_opts=TYPE,SIZE,URL&nfrp=2"
    },
    {
      "query": "World Market",
      "link": "https://www.google.com/search?hl=en&gl=us&q=world+market+marzipan&shoprs=GAIqCG1hcnppcGFuMhAIAhIMV29ybGQgTWFya2V0WMuLIWAB&sa=X&ved=2ahUKEwinlvfQsoiJAxWeF2IAHVDxEO8Qip4GKBd6BAgUED8",
      "serpapi_link": "https://serpapi.com/search.json?device=desktop&engine=google&gl=us&google_domain=google.com&hl=en&location=Austin%2CTexas%2CUnited+States&q=world+market+marzipan",
      "thumbnail": "https://encrypted-tbn1.gstatic.com/faviconV2?url=http://www.worldmarket.com&client=SHOPPING&size=32&type=FAVICON&fallback_opts=TYPE,SIZE,URL&nfrp=2"
    },
    {
      "query": "H-E-B",
      "link": "https://www.google.com/search?hl=en&gl=us&q=h-e-b+marzipan&shoprs=GAIqCG1hcnppcGFuMgkIAhIFSC1FLUJYy4shYAE&sa=X&ved=2ahUKEwinlvfQsoiJAxWeF2IAHVDxEO8Qip4GKBh6BAgUEEE",
      "serpapi_link": "https://serpapi.com/search.json?device=desktop&engine=google&gl=us&google_domain=google.com&hl=en&location=Austin%2CTexas%2CUnited+States&q=h-e-b+marzipan",
      "thumbnail": "https://encrypted-tbn0.gstatic.com/faviconV2?url=https://www.heb.com&client=SHOPPING&size=32&type=FAVICON&fallback_opts=TYPE,SIZE,URL&nfrp=2"
    },
    {
      "query": "eBay",
      "link": "https://www.google.com/search?hl=en&gl=us&q=ebay+marzipan&shoprs=GAIqCG1hcnppcGFuMggIAhIEZUJheVjLiyFgAQ&sa=X&ved=2ahUKEwinlvfQsoiJAxWeF2IAHVDxEO8Qip4GKBl6BAgUEEM",
      "serpapi_link": "https://serpapi.com/search.json?device=desktop&engine=google&gl=us&google_domain=google.com&hl=en&location=Austin%2CTexas%2CUnited+States&q=ebay+marzipan",
      "thumbnail": "https://encrypted-tbn1.gstatic.com/faviconV2?url=https://www.ebay.com&client=SHOPPING&size=32&type=FAVICON&fallback_opts=TYPE,SIZE,URL&nfrp=2"
    },
    {
      "query": "thetasteofgermany.com",
      "link": "https://www.google.com/search?hl=en&gl=us&q=thetasteofgermany.com+marzipan&shoprs=GAIqCG1hcnppcGFuMhkIAhIVdGhldGFzdGVvZmdlcm1hbnkuY29tWMuLIWAB&sa=X&ved=2ahUKEwinlvfQsoiJAxWeF2IAHVDxEO8Qip4GKBp6BAgUEEU",
      "serpapi_link": "https://serpapi.com/search.json?device=desktop&engine=google&gl=us&google_domain=google.com&hl=en&location=Austin%2CTexas%2CUnited+States&q=thetasteofgermany.com+marzipan",
      "thumbnail": "https://encrypted-tbn2.gstatic.com/faviconV2?url=https://www.thetasteofgermany.com&client=SHOPPING&size=32&type=FAVICON&fallback_opts=TYPE,SIZE,URL&nfrp=2"
    }
  ],
  "discussions_and_forums": [
    {
      "title": "Artisanal homemade marzipan",
      "link": "https://www.reddit.com/r/recipes/comments/yt7eri/artisanal_homemade_marzipan/",
      "date": "1y ago",
      "extensions": [
        "r/recipes",
        "50+ comments"
      ],
      "source": "Reddit"
    },
    {
      "title": "What is almond paste? Marzipan?",
      "link": "https://2peasrefugees.boards.net/thread/145630/almond-paste-marzipan",
      "date": "4mo ago",
      "source": "2Peas Refugees"
    },
    {
      "title": "What is Marzipan called in America?",
      "link": "https://www.quora.com/What-is-Marzipan-called-in-America",
      "date": "2y ago",
      "extensions": [
        "2 answers"
      ],
      "source": "Quora"
    }
  ],
  "things_to_know": {
    "buttons": [
      {
        "text": "Nationality",
        "subtitle": "What Nationality Is Marzipan?",
        "title": "History Of Marzipan - Hermine's Old World Confection",
        "link": "https://marzipanlove.com/history-of-marzipan/#:~:text=Although%20it%20is%20believed%20to,Baltic%20Sea%20region%20of%20Germany.",
        "displayed_link": "https://marzipanlove.com \u203a history-of-marzipan",
        "snippet": "Although it is believed to have originated in Persia (present-day Iran) and to have been introduced to Europe through the Turks, there is some dispute between Hungary and Italy over its origin. Marzipan became a specialty of the Baltic Sea region of Germany.",
        "snippet_highlighted_words": [
          "believed to have originated in Persia (present-day Iran) and to have been introduced to Europe through the Turks, there is some dispute between Hungary and Italy over its origin"
        ],
        "favicon": "https://serpapi.com/searches/670a2f6ba775f2c583499ec8/images/f8a266dd3f351a077dca135221b1e4e7e96958546b8d04e2508b39a693817ae3809e61032d52e829.png",
        "source": "marzipanlove.com",
        "search_link": "https://www.google.com/search?sca_esv=8568a6baa21243e5&hl=en&gl=us&q=what+nationality+is+marzipan&sa=X&ved=2ahUKEwinlvfQsoiJAxWeF2IAHVDxEO8QrooIegQIDRAF",
        "serpapi_search_link": "https://serpapi.com/search.json?device=desktop&engine=google&gl=us&google_domain=google.com&hl=en&location=Austin%2CTexas%2CUnited+States&q=what+nationality+is+marzipan"
      },
      {
        "text": "Recipes",
        "subtitle": "Marzipan Recipe",
        "thumbnail": "https://serpapi.com/searches/670a2f6ba775f2c583499ec8/images/f8a266dd3f351a077dca135221b1e4e720f77f426eea120c505147304501e822855319bc9bbb6916.png",
        "web_links": [
          {
            "title": "Best Marzipan Recipe (Almond Paste) - Elavegan",
            "snippet": "This traditional German Marzipan recipe is naturally egg-free, vegan, gluten-free, and optionally paleo and Keto...",
            "link": "https://elavegan.com/homemade-marzipan-recipe/",
            "thumbnail": "https://encrypted-tbn0.gstatic.com/images?q=tbn:ANd9GcSuvhK7rvgiDQn7v40igsRvgRmFKQ6iEq35h5dcBjvGDUqpcipBmnNdZSZr1Rc",
            "source": "Elavegan",
            "source_thumbnail": "https://serpapi.com/searches/670a2f6ba775f2c583499ec8/images/f8a266dd3f351a077dca135221b1e4e720f77f426eea120c8c0be0b2a71bf241075f9f1460acc6644649577e364599b7d847381967238ee7.png"
          },
          {
            "title": "Homemade Marzipan (Almond Paste) - The Daring Gourmet",
            "snippet": "Marzipan Recipe. Let's get started! Add the almond flour to a food processor. Add the powdered sugar to the almond...",
            "link": "https://www.daringgourmet.com/how-to-make-marzipan-almond-paste/",
            "thumbnail": "https://encrypted-tbn0.gstatic.com/images?q=tbn:ANd9GcTowsz9AaPTIqrtpOPr2bRA7f_Gdhbnw8g5Nd6OLilwPN8PHuWBj17Zm7dmUkE",
            "source": "The Daring Gourmet",
            "source_thumbnail": "https://serpapi.com/searches/670a2f6ba775f2c583499ec8/images/f8a266dd3f351a077dca135221b1e4e720f77f426eea120c8c0be0b2a71bf24137ad7133499fd843122bde06837963b66e35763ba785c13c.png"
          }
        ],
        "search_link": "https://www.google.com/search?sca_esv=8568a6baa21243e5&hl=en&gl=us&q=marzipan+recipe&sa=X&ved=2ahUKEwinlvfQsoiJAxWeF2IAHVDxEO8QrooIegQIDRAK",
        "serpapi_search_link": "https://serpapi.com/search.json?device=desktop&engine=google&gl=us&google_domain=google.com&hl=en&location=Austin%2CTexas%2CUnited+States&q=marzipan+recipe"
      },
      {
        "text": "Sweet or not",
        "subtitle": "Is Marzipan Sweet?",
        "title": "Mazapan: A Sweet Taste of Mexico - Medina Baking",
        "link": "https://medinabaking.com/blog/mazapan-a-sweet-taste-of-mexico/#:~:text=Sugar%20is%20the%20sweet%20soul,mouthwatering%20sweetness%20and%20satisfying%20crumble.",
        "displayed_link": "https://medinabaking.com \u203a blog \u203a mazapan-a-sweet-tast...",
        "date": "Oct 16, 2023",
        "snippet": "Sugar is the sweet soul of Mazapan. It's what gives this candy its mouthwatering sweetness and satisfying crumble.",
        "snippet_highlighted_words": [
          "Sugar is the sweet soul of Mazapan"
        ],
        "favicon": "https://serpapi.com/searches/670a2f6ba775f2c583499ec8/images/f8a266dd3f351a077dca135221b1e4e7a477aee240a33d770ff1a549743b1fe3cb90f3b5c349c893.png",
        "source": "medinabaking.com",
        "thumbnail": "https://encrypted-tbn0.gstatic.com/images?q=tbn:ANd9GcRLv_oJ2CXRPGWNrR10aapQDKRzW7tyY0zo-T8ZzaBeElo&s",
        "search_link": "https://www.google.com/search?sca_esv=8568a6baa21243e5&hl=en&gl=us&q=is+marzipan+sweet&sa=X&ved=2ahUKEwinlvfQsoiJAxWeF2IAHVDxEO8QrooIegQIDRAS",
        "serpapi_search_link": "https://serpapi.com/search.json?device=desktop&engine=google&gl=us&google_domain=google.com&hl=en&location=Austin%2CTexas%2CUnited+States&q=is+marzipan+sweet"
      },
      {
        "text": "Healthy or not",
        "subtitle": "Is Marzipan Healthy",
        "title": "Healthy Honey and Almond Marzipan - Cinnamon and Kale",
        "link": "https://www.cinnamonandkale.co.uk/healthy-honey-almond-marzipan/#:~:text=Is%20marzipan%20good%20for%20health,contains%20a%20lot%20of%20sugar.",
        "displayed_link": "https://www.cinnamonandkale.co.uk \u203a healthy-honey-al...",
        "date": "Nov 27, 2019",
        "snippet": "Is marzipan good for health? Marzipan contains almonds which are a good source of minerals such as calcium and magnesium, plus vitamin E. However, bought marzipan also contains a lot of sugar.",
        "snippet_highlighted_words": [
          "Marzipan contains almonds which are a good source of minerals such as calcium and magnesium, plus vitamin E"
        ],
        "favicon": "https://serpapi.com/searches/670a2f6ba775f2c583499ec8/images/f8a266dd3f351a077dca135221b1e4e7a3754bb66b16168153a5743f8c4abc38a2a235f452a321d7.png",
        "source": "cinnamonandkale.co.uk",
        "thumbnail": "https://encrypted-tbn0.gstatic.com/images?q=tbn:ANd9GcQMMoU78rOXFTdiDcYJK-1Mnr3YK0I7Up-1xm4ZEWzmp2jf&s",
        "search_link": "https://www.google.com/search?sca_esv=8568a6baa21243e5&hl=en&gl=us&q=is+marzipan+healthy&sa=X&ved=2ahUKEwinlvfQsoiJAxWeF2IAHVDxEO8QrooIegQIDRAa",
        "serpapi_search_link": "https://serpapi.com/search.json?device=desktop&engine=google&gl=us&google_domain=google.com&hl=en&location=Austin%2CTexas%2CUnited+States&q=is+marzipan+healthy"
      },
      {
        "text": "Origins",
        "subtitle": "Where Is Marzipan From",
        "search_link": "https://www.google.com/search?sca_esv=8568a6baa21243e5&hl=en&gl=us&q=where+is+marzipan+from&sa=X&ved=2ahUKEwinlvfQsoiJAxWeF2IAHVDxEO8QrooIegQIDRAg",
        "serpapi_search_link": "https://serpapi.com/search.json?device=desktop&engine=google&gl=us&google_domain=google.com&hl=en&location=Austin%2CTexas%2CUnited+States&q=where+is+marzipan+from"
      },
      {
        "text": "Pronunciation",
        "subtitle": "How To Pronounce Marzipan",
        "thumbnail": "https://ssl.gstatic.com/dictionary/static/pronunciation/20180801/desktop/sil.svg",
        "search_link": "https://www.google.com/search?sca_esv=8568a6baa21243e5&hl=en&gl=us&q=How+to+pronounce+Marzipan&si=ACC90nxcfzw6qM97V1RqBRZlJw5oOfMBZubr5HbnOuz_-dDMzQ1k3m6DU14e6F1mLWIG0Vl4rAd7lSYCyb6q8gmzCsulm1dYC5uu2s9Qqpr8Oj2yVtd4f43rdTH1ehQN4t1JSYRx9UjxVSN97I5H1jgitOMcfXh6uA%3D%3D&sa=X&ved=2ahUKEwinlvfQsoiJAxWeF2IAHVDxEO8QrooIegQIDRAl",
        "serpapi_search_link": "https://serpapi.com/search.json?device=desktop&engine=google&gl=us&google_domain=google.com&hl=en&location=Austin%2CTexas%2CUnited+States&q=How+to+pronounce+Marzipan&si=ACC90nxcfzw6qM97V1RqBRZlJw5oOfMBZubr5HbnOuz_-dDMzQ1k3m6DU14e6F1mLWIG0Vl4rAd7lSYCyb6q8gmzCsulm1dYC5uu2s9Qqpr8Oj2yVtd4f43rdTH1ehQN4t1JSYRx9UjxVSN97I5H1jgitOMcfXh6uA%3D%3D"
      }
    ]
  },
  "pagination": {
    "current": 1,
    "next": "https://www.google.com/search?q=marzipan&sca_esv=8568a6baa21243e5&hl=en&gl=us&ei=bC8KZ6ewEJ6viLMP0OLD-A4&start=10&sa=N&sstk=AagrsujMFdZJJiLM12wiDR_HMPavUgTb-HLnAMoLTOdGRs5f9LuK5ls1yYQ45r6VWnSlKbeRxy20BBqzwKPPdPR5GfPXZk6MW3mNWQ&ved=2ahUKEwinlvfQsoiJAxWeF2IAHVDxEO8Q8NMDegQICBAW",
    "other_pages": {
      "2": "https://www.google.com/search?q=marzipan&sca_esv=8568a6baa21243e5&hl=en&gl=us&ei=bC8KZ6ewEJ6viLMP0OLD-A4&start=10&sa=N&sstk=AagrsujMFdZJJiLM12wiDR_HMPavUgTb-HLnAMoLTOdGRs5f9LuK5ls1yYQ45r6VWnSlKbeRxy20BBqzwKPPdPR5GfPXZk6MW3mNWQ&ved=2ahUKEwinlvfQsoiJAxWeF2IAHVDxEO8Q8tMDegQICBAE",
      "3": "https://www.google.com/search?q=marzipan&sca_esv=8568a6baa21243e5&hl=en&gl=us&ei=bC8KZ6ewEJ6viLMP0OLD-A4&start=20&sa=N&sstk=AagrsujMFdZJJiLM12wiDR_HMPavUgTb-HLnAMoLTOdGRs5f9LuK5ls1yYQ45r6VWnSlKbeRxy20BBqzwKPPdPR5GfPXZk6MW3mNWQ&ved=2ahUKEwinlvfQsoiJAxWeF2IAHVDxEO8Q8tMDegQICBAG",
      "4": "https://www.google.com/search?q=marzipan&sca_esv=8568a6baa21243e5&hl=en&gl=us&ei=bC8KZ6ewEJ6viLMP0OLD-A4&start=30&sa=N&sstk=AagrsujMFdZJJiLM12wiDR_HMPavUgTb-HLnAMoLTOdGRs5f9LuK5ls1yYQ45r6VWnSlKbeRxy20BBqzwKPPdPR5GfPXZk6MW3mNWQ&ved=2ahUKEwinlvfQsoiJAxWeF2IAHVDxEO8Q8tMDegQICBAI",
      "5": "https://www.google.com/search?q=marzipan&sca_esv=8568a6baa21243e5&hl=en&gl=us&ei=bC8KZ6ewEJ6viLMP0OLD-A4&start=40&sa=N&sstk=AagrsujMFdZJJiLM12wiDR_HMPavUgTb-HLnAMoLTOdGRs5f9LuK5ls1yYQ45r6VWnSlKbeRxy20BBqzwKPPdPR5GfPXZk6MW3mNWQ&ved=2ahUKEwinlvfQsoiJAxWeF2IAHVDxEO8Q8tMDegQICBAK",
      "6": "https://www.google.com/search?q=marzipan&sca_esv=8568a6baa21243e5&hl=en&gl=us&ei=bC8KZ6ewEJ6viLMP0OLD-A4&start=50&sa=N&sstk=AagrsujMFdZJJiLM12wiDR_HMPavUgTb-HLnAMoLTOdGRs5f9LuK5ls1yYQ45r6VWnSlKbeRxy20BBqzwKPPdPR5GfPXZk6MW3mNWQ&ved=2ahUKEwinlvfQsoiJAxWeF2IAHVDxEO8Q8tMDegQICBAM",
      "7": "https://www.google.com/search?q=marzipan&sca_esv=8568a6baa21243e5&hl=en&gl=us&ei=bC8KZ6ewEJ6viLMP0OLD-A4&start=60&sa=N&sstk=AagrsujMFdZJJiLM12wiDR_HMPavUgTb-HLnAMoLTOdGRs5f9LuK5ls1yYQ45r6VWnSlKbeRxy20BBqzwKPPdPR5GfPXZk6MW3mNWQ&ved=2ahUKEwinlvfQsoiJAxWeF2IAHVDxEO8Q8tMDegQICBAO",
      "8": "https://www.google.com/search?q=marzipan&sca_esv=8568a6baa21243e5&hl=en&gl=us&ei=bC8KZ6ewEJ6viLMP0OLD-A4&start=70&sa=N&sstk=AagrsujMFdZJJiLM12wiDR_HMPavUgTb-HLnAMoLTOdGRs5f9LuK5ls1yYQ45r6VWnSlKbeRxy20BBqzwKPPdPR5GfPXZk6MW3mNWQ&ved=2ahUKEwinlvfQsoiJAxWeF2IAHVDxEO8Q8tMDegQICBAQ",
      "9": "https://www.google.com/search?q=marzipan&sca_esv=8568a6baa21243e5&hl=en&gl=us&ei=bC8KZ6ewEJ6viLMP0OLD-A4&start=80&sa=N&sstk=AagrsujMFdZJJiLM12wiDR_HMPavUgTb-HLnAMoLTOdGRs5f9LuK5ls1yYQ45r6VWnSlKbeRxy20BBqzwKPPdPR5GfPXZk6MW3mNWQ&ved=2ahUKEwinlvfQsoiJAxWeF2IAHVDxEO8Q8tMDegQICBAS",
      "10": "https://www.google.com/search?q=marzipan&sca_esv=8568a6baa21243e5&hl=en&gl=us&ei=bC8KZ6ewEJ6viLMP0OLD-A4&start=90&sa=N&sstk=AagrsujMFdZJJiLM12wiDR_HMPavUgTb-HLnAMoLTOdGRs5f9LuK5ls1yYQ45r6VWnSlKbeRxy20BBqzwKPPdPR5GfPXZk6MW3mNWQ&ved=2ahUKEwinlvfQsoiJAxWeF2IAHVDxEO8Q8tMDegQICBAU"
    }
  },
  "serpapi_pagination": {
    "current": 1,
    "next_link": "https://serpapi.com/search.json?device=desktop&engine=google&gl=us&google_domain=google.com&hl=en&location=Austin%2CTexas%2CUnited+States&q=marzipan&start=10",
    "next": "https://serpapi.com/search.json?device=desktop&engine=google&gl=us&google_domain=google.com&hl=en&location=Austin%2CTexas%2CUnited+States&q=marzipan&start=10",
    "other_pages": {
      "2": "https://serpapi.com/search.json?device=desktop&engine=google&gl=us&google_domain=google.com&hl=en&location=Austin%2CTexas%2CUnited+States&q=marzipan&start=10",
      "3": "https://serpapi.com/search.json?device=desktop&engine=google&gl=us&google_domain=google.com&hl=en&location=Austin%2CTexas%2CUnited+States&q=marzipan&start=20",
      "4": "https://serpapi.com/search.json?device=desktop&engine=google&gl=us&google_domain=google.com&hl=en&location=Austin%2CTexas%2CUnited+States&q=marzipan&start=30",
      "5": "https://serpapi.com/search.json?device=desktop&engine=google&gl=us&google_domain=google.com&hl=en&location=Austin%2CTexas%2CUnited+States&q=marzipan&start=40",
      "6": "https://serpapi.com/search.json?device=desktop&engine=google&gl=us&google_domain=google.com&hl=en&location=Austin%2CTexas%2CUnited+States&q=marzipan&start=50",
      "7": "https://serpapi.com/search.json?device=desktop&engine=google&gl=us&google_domain=google.com&hl=en&location=Austin%2CTexas%2CUnited+States&q=marzipan&start=60",
      "8": "https://serpapi.com/search.json?device=desktop&engine=google&gl=us&google_domain=google.com&hl=en&location=Austin%2CTexas%2CUnited+States&q=marzipan&start=70",
      "9": "https://serpapi.com/search.json?device=desktop&engine=google&gl=us&google_domain=google.com&hl=en&location=Austin%2CTexas%2CUnited+States&q=marzipan&start=80",
      "10": "https://serpapi.com/search.json?device=desktop&engine=google&gl=us&google_domain=google.com&hl=en&location=Austin%2CTexas%2CUnited+States&q=marzipan&start=90"
    }
  }
}